{
  "sources": [
    {
      "title": "小众软件",
      "feedUrl": "http://feeds.appinn.com/appinns/",
      "siteUrl": "https://www.appinn.com",
      "articles": [
        {
          "id": "https://www.appinn.com/?p=39295",
          "author": "青小蛙",
          "description": "GoodSync 11 是著名的文件同步工具，支持 Windows、macOS 系统，它可以让不同的设备，根据设定的规则，自动同步、备份文件，并且可以使用 iPhone、Android 设备浏览电脑上",
          "link": "https://www.appinn.com/goodsync-11-free-for-a-limited-time/",
          "publishedOn": "2021-07-14T04:53:35.000Z",
          "wordCount": 1557,
          "title": "GoodSync 11 限免，著名文件同步工具，可同步 5 台设备，1 年免费，自带内网穿透"
        },
        {
          "id": "https://www.appinn.com/?p=39290",
          "author": "青小蛙",
          "description": "ViennaRSS 是一款 macOS 下的开源 RSS 阅读器，支持本地订阅 RSS，还支持 5 大在线阅读器，包括 BazQux、FreshRSS、FeedHQ、InoReader、TheOldR",
          "link": "https://www.appinn.com/viennarss-for-macos/",
          "publishedOn": "2021-07-13T08:38:51.000Z",
          "wordCount": 1272,
          "title": "ViennaRSS – 开源 RSS 阅读器，支持 5 大在线阅读器[macOS]"
        },
        {
          "id": "https://www.appinn.com/?p=39275",
          "author": "开发者推荐账号",
          "description": "平时在公司，想要把一些画册、手册、文档资料发给客户，或内部阅读，总是把 Word 或 PDF 发来发去，他人还得下载才能看，当文件过大时，在软件中传送也常遇到问题，非常不利于传播，而一般像在微信中转发",
          "link": "https://www.appinn.com/yunzhan365-202107/",
          "publishedOn": "2021-07-13T02:00:00.000Z",
          "wordCount": 1455,
          "title": "云展网 送VIP会员 – 在线转换 PDF 文档为 3D 翻页书 (生成链接二维码/方便微信转发分享)"
        },
        {
          "id": "https://www.appinn.com/?p=39268",
          "author": "青小蛙",
          "description": "岁月相册 是一款 Android 上的相册应用，支持 HEIF/HEIC，启动速度快，预览图片速度快，打开大图速度快，总之就是快，快到启动画面动画都看不到。自称“出道即巅峰”、“已经超越业界大部分对手",
          "link": "https://www.appinn.com/years-0-1-0-alpha10/",
          "publishedOn": "2021-07-12T08:53:58.000Z",
          "wordCount": 1351,
          "title": "岁月相册 – 支持 HEIF/HEIC 格式，出道即巅峰，真的很快很快的 Android 相册应用"
        },
        {
          "id": "https://www.appinn.com/?p=39264",
          "author": "青小蛙",
          "description": "New Folder Wizard 是一款批量创建新文件夹的 Windows 工具，可以简单的通过序号排列创建文件夹，还可以通过文本文件自定义批量创建文件夹。@Appinn 前几天有位同学求“tab",
          "link": "https://www.appinn.com/new-folder-wizard-windows/",
          "publishedOn": "2021-07-12T06:06:36.000Z",
          "wordCount": 1324,
          "title": "New Folder Wizard – 批量创建新文件夹神器[Windows]"
        },
        {
          "id": "https://www.appinn.com/?p=39260",
          "author": "青小蛙",
          "description": "有期是一款用来记录食物、物品保质期、证件到期日的 iPhone、Android 应用，简单易用、免费，拥有临期提醒功能，可以用来记录一切有期限的事物，比如食物、护肤品、身份证、订阅制软件、优惠券等。@",
          "link": "https://www.appinn.com/expify-you-qi-app/",
          "publishedOn": "2021-07-11T04:17:16.000Z",
          "wordCount": 1208,
          "title": "有期 – 记录保质期、到期日，提醒食物、物品、证件、订阅、优惠券到期[iPhone/Android]"
        },
        {
          "id": "https://www.appinn.com/?p=39257",
          "author": "青小蛙",
          "description": "这是一篇发布在讨论组的帖子，原标题： 那些好玩又有趣的手机游戏，作者 @suntrise 前言 这是写给我自己的游戏回忆录 这几年玩过很多很有趣的游戏，不过这两年由于各种原因，把它们都淡",
          "link": "https://www.appinn.com/suntrise-games/",
          "publishedOn": "2021-07-09T02:36:00.000Z",
          "wordCount": 1222,
          "title": "suntrise 的游戏回忆录：那些好玩又有趣的手机游戏"
        },
        {
          "id": "https://www.appinn.com/?p=39241",
          "author": "数码荔枝",
          "description": "白描（miao），作为一款出色的 OCR 扫描识别神器。具备高准确度的文字识别、文字翻译、表格识别转 Excel、文件批量扫描等功能。 相信很多用户听说过这款 App，口碑相当不错。文档扫描识别翻译个",
          "link": "https://www.appinn.com/baimiao-app-202107/",
          "publishedOn": "2021-07-08T07:42:45.000Z",
          "wordCount": 1425,
          "title": "下周一涨价倒计时！白描 App 永久会员折扣，别错过"
        },
        {
          "id": "https://www.appinn.com/?p=39236",
          "author": "青小蛙",
          "description": "Sumatra PDF 是一款有着 15 年历史的老牌、轻量级、开源 PDF 阅读器，还支持电子书（ePub, Mobi）、XPS、DjVu、CHM、Comic Book (CBZ and CBR)",
          "link": "https://www.appinn.com/sumatra-pdf-3-3/",
          "publishedOn": "2021-07-08T03:51:21.000Z",
          "wordCount": 1472,
          "title": "Sumatra PDF 3.3 版本发布，拥有 15 年历史的轻量级开源 PDF 阅读器"
        },
        {
          "id": "https://www.appinn.com/?p=39219",
          "author": "开发者推荐账号",
          "description": "随着网络时代的发展与进步，我们的学习工作和生活早已离不开互联网，智能家居、网上购物、日常出行都需要互联网的支持。互联网切切实实地给生活带来了诸多便利。 那大家有没有碰到过这么一个情况呢？当我们在使用手",
          "link": "https://www.appinn.com/what-does-404-mean-upyun/",
          "publishedOn": "2021-07-07T12:01:56.000Z",
          "wordCount": 1646,
          "title": "【白话科普】上网时遇到的 404 是什么意思？"
        }
      ]
    },
    {
      "title": "人人都是产品经理",
      "feedUrl": "http://www.woshipm.com/feed",
      "siteUrl": "http://www.woshipm.com",
      "articles": [
        {
          "id": "http://www.woshipm.com/?p=4856104",
          "author": "流量星球",
          "description": "编辑导语：SAAS是国内互联网在特殊环境下成为热门的一大营销方式。但你了解SAAS吗？知道如何用它做推广吗？为你一起来看看如何用SAAS进行内容营销吧。\n\n\nSAAS在国外大行其道，但很长一段时间在国内却一直不温不火，疫情的出现让SAAS成为热门，但在国内互联网但特殊环境下，很多厂商都苦于SAAS的营销推广。\nsaas营销方式一般有4种：\n搜索引擎seo/sem\n线下会议\n信息流\n内容营销\n国内的产品一般还是以seo/sem、信息流和线下会议为主，靠内容营销的还比较少。但现状是seo/sem是pc端为主，pc端流量都被移动分走了，而现在的某度又搞了基木鱼，很多公司效果都很差。我知道的一个公司自从搞了基木鱼后，每月线索都腰斩了。\n而信息流主要是腾讯、头条等平台，因为是以小广告的形式，用户对产品了解很少，而且用户并不精准，所以获客成本很高，转化率低。\n线下会议则饱受争议，基本都是赔钱赚吆喝，saas公司没赚到钱，都让举办会议都公司赚去了。而且线下会议要场地，要时间，来的人还少。\n内容营销在国外非常的受欢迎，在国内可以做起来吗？作为一个有实操经验的saas内容营销者，我可以肯定的说是可以的。在国内之所以做的比较少，这和国内的内容环境有关系。\n一、国内的内容环境\npc互联网时期，网站功能都大同小异，核心差异是内容，内容形式也比较少，图文是主流。不同行业，不同群体，各做各的内容。\n而到移动互联网，各种app层出不穷，好玩的功能成为吸引用户的手段。与此同时，一些垂直内容平台也纷纷做公众号和app，pc端网站流量很少了。\n移动端的内容形式有图文、音频和视频，最开始是图文，后来音频火过一段，到最近的视频内容成为热门。\n但随着移动互联网的发展网络，人口红利没了，产品功能形态基本已经没有创新空间了，但用户留存在不断下降。\n微信的创造者张小龙曾经说：好的产品是用完即走的！所以微信做的很克制，其他…",
          "link": "http://www.woshipm.com/pd/4856104.html",
          "publishedOn": "2021-07-14T12:46:36.000Z",
          "wordCount": 274,
          "title": "SAAS到底怎么做推广？答案是内容营销！"
        },
        {
          "id": "http://www.woshipm.com/it/4868494.html",
          "author": "接地气的陈老师",
          "description": "编辑导语：在数据分析领域中，面对多因素归因总是很难分析的。尤其是在临近年底，面对各大岗位的人，都会跑来喊你量化一下，那该如何量化啊？\n\n\n数据分析领域有几个经典的终极难题。多影响因素归因，绝对是其中最让人头大的。特别是临近年底，品牌、售后、客服、供应链、运营、产品、商品管理都会跑来，问：“今年业绩不错呀，那么问题便来了：今年公司多赚的10个亿，到底几个亿归功于品牌，到底几个亿归功于供应……请量化分析一下，谢谢”。\n那么，到底该怎么分析呢？今天我们详细讲解一下。\n一、多影响因素归因的表面\n为啥这个问题是终极难题，只要做一个实验，马上便知道。\n同学们可以亲自试试哦。\n第一步：请闭上眼睛第二步：回忆淘宝里最近买的一件商品。\n第三步：在脑海里回忆该商品的名称、包装、价格、品牌、客服小妹声音……\n第四步：睁开眼，告诉自己：我为这个商品付费的XXX钱，其中有X%是付给名称，X%付给包装，X%付费给商品上blingbling的广告，X%付给快递叔叔……\n答得出来不？\n不但很难答出来，估计很多同学连最近买的是啥都不记得了。\n消费者不是所有消费都理性。\n消费者不是所有商品都重视。\n商家提供的品牌、服务、产品本身就是一个整体。\n因此站在消费者角度，这个问题从源头上就不成立。特别是啤酒瓜子矿泉水一类的快消类产品。价格低，消费频次高，冲动消费多，心情好了就买点，心情不好了也买点，因此很难讲清楚。大宗耐用品，比如房子、车子可能思考的多一些，有一定概率区分出来，但是仍然很难量化到每个因素的得分（如果怀疑这点的，想象你结婚那一刻有多纠结，就秒懂了，哈哈）。\n那么问题来了：为啥明知道分不清楚，各个部门还一而再、再而三要求分家呢？\n这就触及到问题的本质：大家的屁股坐在哪里。\n二、多影响因素归因的本质\n表象上看，多影响因素归因，难在很难拆解数据。\n本质上看，多影响因素归因，只是部门间分赃不均的结果。\n每个部门…",
          "link": "http://www.woshipm.com/data-analysis/4868494.html",
          "publishedOn": "2021-07-14T12:40:42.000Z",
          "wordCount": 286,
          "title": "数据分析终极一问：多影响因素下，到底如何归因？！"
        },
        {
          "id": "http://www.woshipm.com/?p=4868940",
          "author": "WOWDesign",
          "description": "编辑导语：设计师日常需要与客户沟通需求，但总有些需求方的要求，无法达到，面对需求方的反馈，该如何清晰地表达自己的想法呢？\n\n\n作为设计师你一定也遇到过产品经理对你的设计“指手画脚”，互相僵持不下，沟通效率极低的情况；也常在工作中面对别人的反馈时，不知道如何去清晰的表达自己的想法。由此可见，设计师在职场中学会沟通技巧愈发的重要。\n在大多数企业中，设计师更多是以资源项的角色存在，也就是为需求部门提供设计服务，协同推进产品落地，通过产品落地带来商业价值并实现设计变现。\n\n（需求方与资源方关系图）\n在需求前期阶段，设计师需要和产品参与到需求的沟通、了解业务情况，包括目标方向确定、用户场景分析、需求拆解等。在需求设计阶段，设计师需要依据需求前期的沟通结果，进行设计分析并输出设计方案。在需求落地阶段，设计师需要就设计方案与开发进行沟通，并全程跟进走查。因此，设计是一个多方协作的过程，那么设计师怎样沟通能提升效率呢？\n\n（设计流程-双钻模型图）\n一、达成共识三部曲：听、问、复述\n1. 先听\n在听的时候，学会先清空自己，不带任何自我主观的认识，因为对于每一次全新的需求，你永远都没有需求方更清楚其背景和目的，最好的方式就是仔细听，记详细。\n2. 后问\n专注听后，可以把自己记下来的疑问提出来确认清楚，比如需求逻辑、目的、场景等。\n有疑问要当场提出来，不要遗留问题，因为你的疑问也有可能是别人的疑问。\n3. 复述\n尝试用自己的话把对需求的理解和想要的功能做一遍复述，看双方是否理解一致。并且与业务方确认好时间、对接人，后续有疑问的时候可以直接进行沟通。\n二、时刻围绕根本目的\n设计前，不要只看表面现象，要去想需求方的目的，设计只是手段。\n设计师要对需求有足够的了解，比如这个需求要解决什么问题，核心的目的是什么、目标用户有哪些、使用场景是什么、关联因素有什么、是否有特殊要求等，这些是设计方案的支撑，不然…",
          "link": "http://www.woshipm.com/it/4868940.html",
          "publishedOn": "2021-07-14T12:24:00.000Z",
          "wordCount": 285,
          "title": "设计师怎样沟通才能让自己更轻松？"
        },
        {
          "id": "http://www.woshipm.com/it/4868229.html",
          "author": "公众号：产品大峡谷",
          "description": "编辑导语：在进行业务调研时，你是否会由于非科班出身，对于一些金融机构概念不太了解呢？作者也遇到过类似的情况，在文中总结了一些金融机构的基础概念，与你分享。\n\n\n前两天在业务调研时，涉及到关于金融机构的一些概念知识，由于镜同学原先不是金融出身，所以对金融机构也不甚了解，对什么政策银行，商业银行等基础的知识也是小白看戏，就趁课下时间，搜集学习了一些信息（参考网上知识、线下交流会等），而后我发现这些基础的知识，不仅对金融领域的产品经理很重要，对于普通的产品同学也是很有价值的，因此分享一下有关产品笔记。\n什么是金融机构呢？金融机构（Financial Institution）是指从事金融业有关的金融中介机构，为金融体系的一部分，金融业包括银行、证券、保险、信托、基金等行业。\n一、按照按地位和功能划分。\n1. 中央银行\n中央银行，中国的中央银行也就是指中国人民银行。\n咱们俗称“央行”，央行属于管理机构，是国家中居主导地位的金融中心机构，是国家干预和调控国民经济发展的重要工具。负责制定并执行国家货币信用政策，独具货币发行权，实行金融监管。\n中央银行是发行的银行，是指中央银行垄断货币发行权，是一国或某一货币联盟唯一授权的货币发行机构，央行体现着统一控制、统一货币、统一管理的国家意志，中央银行职能主要以制定、执行货币政策，对金融机构活动进行领导、管理和监督，是一个“管理金融活动的银行”。\n央行除了为政府、商业银行服务职能外，重要的是行使监管职能，对商业银行和其他金融机构的监管外，中央银行以国家货币政策制定者和执行者的身份，通过金融手段，对全国的货币、信用活动进行有目的、有目标的调节和控制，进而影响国家宏观经济，促进整个国民经济健康发展，实现其预期的货币政策目标。\n需要提醒的是， 央行归属国务院直接领导，并且，央行是指中国人民银行，是国务院组成部门，为正部级；央行与中国银行可不是一个啊，后者…",
          "link": "http://www.woshipm.com/pd/4868229.html",
          "publishedOn": "2021-07-14T12:02:54.000Z",
          "wordCount": 270,
          "title": "建议收藏：一文彻底说清什么是金融机构"
        },
        {
          "id": "http://www.woshipm.com/it/4872687.html",
          "author": "深燃",
          "description": "编辑导语：近来，网约车市场格局发生了较大变化，而在网约车烧钱补贴背后，我们应该知道，网约车平台若想得以长期发展，则应当在运营效率、用户体验提升、行业规范等方面着力改善。本篇文章里，作者针对网约车市场现状做了一定解读，一起来看一下。\n\n\n网约车的补贴大战又来了：拉新就送红包；注册APP，优惠券十连送根本用不过来；打个车单单立减……\n很长一段时间以来，网约车行业滴滴一家独大。嘀嗒出行、首汽约车、曹操出行、T3出行中最高活跃用户仅在千万级别，一众新进入者用户在数十万量级，不及头部公司的一个零头。\n如今千载难逢的机遇终于来了。\n7月4日，各应用商店下架“滴滴出行”APP。7月9日晚间，网信中国发布消息称，因严重违法违规收集使用个人信息，滴滴旗下另外25款APP也被要求下架。\n滴滴下架，消费者们开始寻找可替代的网约车平台。这也让各大网约车公司看到了难得的机会。最近一个星期，市场上突然冒出了十几个大大小小的网约车平台，他们开始扩招司机、疯狂烧钱补贴、加大地推力度，试图抢夺市场。\nT3出行甚至信心满满地发了一条微博，在微博中指出：目前T3已经进入20多个城市，今年会达到48个，基本覆盖全国一二三线城市。而曾经一度下架的美团打车APP，如今也重新“复活”，甚至把业务线拓展到了100个城市之中。\n这些试图分食网约车市场蛋糕的玩家们，真的能打赢这场反攻战吗？烧钱补贴真的能换取用户增长吗？市场心智长期被大品牌占据的当下，这些网约车公司又有可能抢夺多少的市场份额？\n一、抢滩窗口期，二线网约车大反攻\n家住北京的佳佳平日里打车用的是滴滴APP，最近两天，她用起了美团打车。“朋友一直在安利，说美团现在优惠很多，而且响应很快，我就心动了。”\n她给深燃展示了最近在美团打车APP上的两笔消费账单，这两笔账单都是10公里左右的路程，由于平台给出了优厚的新人补贴，其中一单优惠了10元，另一单优惠了14.45元。对…",
          "link": "http://www.woshipm.com/it/4872687.html",
          "publishedOn": "2021-07-14T12:01:19.000Z",
          "wordCount": 285,
          "title": "网约车大战，又来了"
        },
        {
          "id": "http://www.woshipm.com/?p=4862113",
          "author": "汪仔0321",
          "description": "编辑导语：区别于普通的媒介，新媒体的发展，使得用户能够更快地接收到相关信息。而手机短信推送也成为了当前营销的一大方式，短信营销该怎么推送才能更有价值？\n\n\n区别于电视、广播、报纸和杂志这四大传统媒体，手机已经被定义为新时代第五大媒体。随着手机使用率越来越高，手机短信推送（短信营销）也成为了C端运营的主要手段。\n一、什么是短信营销？\n短信营销主要是以移动数据通信为主要技术手段，将短信发送到用户手机中，借此达到营销目的。短信营销具有针对性强、覆盖面广、不可回避型、时间灵活及成本低廉等优势，即便现在垃圾短信满天飞，短信还是最有效的推送渠道。\n二、如何增加转化效能？\n无效曝光是对资源的浪费，用户体验也会很差。这就要求运营人员需要正确使用这个渠道，在避免骚扰用户的前提下，实现ROI（投入产出比）的最优化。\n1. 选择好的推送通道\n流量成本增加，企业发展进入存量时代，不同于增量时代的扩张探索红利，存量时代要求企业纵深发展精耕细作，在此背景下，企业也从原来的效率拉新向以增加存量用户的粘性为目标，收集和运用数据是企业提升营销数字化运营水平的关键点。\n2. 追求高效推送逻辑\n一般的推送路径可分为“推送、点击、跳转下载/打开应用、注册、使用”。\n能清晰看出来，中间过程越繁琐，用户留存就会越低。要有效优化路径，运营同学可以在所选择的推广渠道中嵌入活动页面短链，用户点击短链接可以直接跳转APP中活动页，和传统的路径相比减少了两层流失。\n\n3. 实现裂变营销新玩法\n移动互联网营销的本质，就是裂变营销。\n传统营销方式是走产品研发、渠道推广的路子，在如今互联网高速发展的时代，随着渠道越来越广，传统营销的成本会越来越高，唯有好的内容、社区、裂变，才能做到低成本高质量的发展。\n举个例子，以通过裂变的方式快速成长的拼多多，主要侧重于借助社交关系做裂变，让社交圈内的用户看到这一优惠活动，从帮助他人切入，进行活动和品牌的传播，吸引更多人的注意和参与，每一步都让人有分享的欲望。\n如何让发起裂变用户和接收用户在参与时能有良好的体验，是运营同学需要思考的一点。\n普通的裂变方式，是用户A在APP内发起邀请，生成一个邀请码链接，再通过社交软件发给B、C、D…….\n被发送用户接收到邀请码后，再登录或下载相应的APP，输入邀请码，完成裂变环节。\n相较于普通的裂变方式，运营同学可以去掉一些繁琐的步骤，比如邀请信息，很多用户在被邀请后进入APP很难找到对应填写邀请码的地方，裂变就实现不了闭环，这部分用户还是没有被成功拉进来。\n此外，还可以自动跟踪邀请关系，让邀请人和被邀请人都能在APP内享受优惠到相应的条件，用户体验感上去了，对于运营同学后期的社群建设也有很大的帮助。\n三、合理使用数据平台\n找好了推送方式，我们就要根据所获得的数据进行更详细的运营策略制定。\n以访问分布为例，通过访问地区、访问分布、浏览器分布及操作系统分布数据来看，我们可以清楚的知道用户基本画像，哪些省份的用户活跃度最高，用户更倾向在什么时候打开APP，是安卓端用户占比高还是iOS端用户占比高，通过手机品牌配合近几年各大手机厂商发布的用户报告，可以进一步细化用户画像。\n了解了这部分数据后，运营同学可以有针对性的做出一些优化方案，比如应该给哪些用户推送什么信息，根据用户画像的差异进行用户分层。\n\n再说说用户留存，用户来了就走，这是最没有意义的营销，对于任何企业来说，留住一个老用户的成本远远低于获取新用户的成本，那么就要求运营同学要重点关注新用户的质量，做好用户粘性。\n因为APP内拉新促活的路径不单一，所以每一个环节的用户留存并不可能做到百分之百，运营同学经常会关注留存率的问题，所谓的留存用户是在某段时间内的新增用户，经过一段时间后，又继续使用的用户占当时新增用户的比例即是留存率。\n例如，5月份新增用户200人，这200名用户在6月份启动过应用的有100人，7月份启动过应用的有80人，8月份启动过应用的有50人；则5月新增用户一个月后的留存率是50%，两个月后的留存率是40%，三个月后的留存率是25%。\n\n四、总结\n短信推送只是一种营销手段，虽然效果明显但也不能一味的依赖，短信推送可以非常快速高效的让用户了解到产品，依靠运营同学根据不同场景做出的策略调整，才会让用户更加依赖产品。\n \n本文由 @北北君 原创发布于人人都是产品经理，未经作者许可，禁止转载。\n题图来自Unsplash，基于 CC0 协议",
          "link": "http://www.woshipm.com/operate/4862113.html",
          "publishedOn": "2021-07-14T11:50:13.000Z",
          "wordCount": 251,
          "title": "如何让短信推送更有价值？"
        },
        {
          "id": "http://www.woshipm.com/it/4872320.html",
          "author": "雷科技",
          "description": "编辑导语：HD版应用成为过去了吗？随着HD版应用更新收益的下降，以及开发者对成本可控性要求的提出，HD版应用逐渐停更。那么，开发者是否需要针对平板用户做出适配？本篇文章里，作者针对HD版应用的相应现状进行了解读，一起来看一下。\n\n\n与智能手机不同，平板电脑定位于笔记本电脑和手机之间，屏幕尺寸大于手机，却又小于笔记本电脑。为了提供更好的应用体验，软件开发者们针对平板电脑进行了适配，推出了HD版。\nHD是英文“High Definition”的缩写，译为高分辨率。凡是标有HD字样的应用，基本上都适用于平板电脑。HD版应用的由来，可以追溯到初代iPad，尽管当时所有的iOS应用都可以在iPad上使用，但是用户希望在iPad上使用原生分辨率的应用。于是，软件开发者们便专门为iPad推出了HD版应用。\n其中，腾讯就是最早适配iPad，并推出HD版App的软件开发者之一，例如QQ HD，在iPad上的界面布局比手机版更合理。\n然而，就在去年3月，QQ HD从Apple Store下架。目前，据网友反馈，适用于iPad的QQ HD，登录时会提示账号暂时无法登录，需要将应用升级到最新版本。这也就意味着，腾讯彻底停运了QQ HD版，原QQ HD用户需要迁移至通用版QQ。而通用版QQ iOS版已于2019年8月发布的8.1.3更新中，完美适配了iPad。\n\n一、HD版App已成过去？\n腾讯不再运营QQ HD版，其实是大势所趋。单从技术层面来讲，早期软件开发者之所以单独推出HD版应用，是因为当初开发架构比较落后，无论iOS还是安卓的开发架构，都不能很好地支持多分辨率。\nQQ HD老用户应该知道，这款App更新频率非常低，甚至直接在2019年就已经停更了。事实上，不只是QQ HD，市面上很多HD都已经不再更新，或者说软件开发者已经放弃了对HD版应用的维护和支持。\n为什么后来HD版的应用基本上都停更…",
          "link": "http://www.woshipm.com/it/4872320.html",
          "publishedOn": "2021-07-14T11:36:23.000Z",
          "wordCount": 266,
          "title": "随着QQ HD限制登录，又一个时代结束了"
        },
        {
          "id": "http://www.woshipm.com/?p=4867090",
          "author": "李杭",
          "description": "编辑导语：作为一名项目经理，时常会遇到许多不同的问题，面临项目不知道如何进展该怎么做？作者以大型项目（电力系统）为例，分享其项目实战的经验。\n\n\n大中型项目主要从两个大的层面进行一个是项目、一个是需求，这种方式在大中型的项目中方式将是最好用的，从项目层面来说主要包含三部分项目立项（项目文件、前期会议）、项目实施（项目进度、人员、）项目验收（验收、运营）。\n项目不管是什么大型、中型、小型项目其中一个项目核心因素主要是人员、时间、资金、这三点要素必须要具备。\n在项目的立项阶段首先要知道项目所属是什么类型的项目，其中对于项目的进行大致的判断，对项目进行一个预估所需人力、时间、成本是多少，在现有的条件下能够做的什么程度，这样的程度是否能够满足上级制定的时间，注意一点，千万不要程序员做决定，随口就答应下来。\n说能完成，到最后发现项目已经严重超过了预期，这样的情况是因为期间会不断有新的需求加塞儿，导致越来越多，最后在上线前发现完成不了，这样就不好了。\n如果遇到中途需要对接的项目，这样在前期需要一定时间去获取项目信息数据，以便自己在后期能够将项目顺利的完成验收，这样就需要自己能够将项目进行全面评估。\n以下的几点要素需要去考虑，人员水平怎样，人员配比是否合理，人员的状态，项目进展，项目材料，项目时间，是否有延期交付的因素出现，对于可能出现的延期项目信息，需要进行预警，形成汇总文件进行上报，这样便于以后追踪，同时也能够整个管理层进行关注，保证自己的项目状态是可追踪和透明的。\n接着就是需求，需要对需求有个明确的判断，其中主要包含三个部分：一是可研需求、二是业务需求、三是市场需求。\n其中可研需求主要来源是可研（项目可行性研究），每年年底会进行项目申报，对于申报文件中信息需要自己能够随时了解，在后期这些都是验收的重要参考信息依据，每一条功能点和说明文字、字段、提示、文本框、页面等。\n这些都需要对得…",
          "link": "http://www.woshipm.com/pd/4867090.html",
          "publishedOn": "2021-07-14T11:24:46.000Z",
          "wordCount": 260,
          "title": "项目实战：如何构建大中型系统《二》"
        },
        {
          "id": "http://www.woshipm.com/?p=4867596",
          "author": "文静的小正",
          "description": "编辑导语：你是否会在手忙脚乱或者自己需要时，找不到自己想用的文件？这时候，就需要对你的文件动点手脚，来看看作者分享的一些文件整理方法吧。\n\n\n写在开始：文件整理终究只是方法，最终目的是方便自己寻找文件，方便自己后续的工作。\n一、文件使用场景\n在工作中你是否遇到过这种场景：\n内容改了N版，最后老板说给我把第X版找出来。\n项目第一期结束了，自己产生了一堆过程文件，再次查看时找不到自己的最终文档。\n项目重新开始，需要参考第一期设计的所有内容。\n帮助其他部门临时支持一下，但是年终了需要了解当时的文档\n而一个好的文件整理规范，可以让你在产品设计过程中更好的找到每个版本的文件，可以让你在项目结束/再次重启时对项目有个良好的规划，可以让你知道你到底产出了多少内容。\n总的来说，一个好的文件整理规范是可以节省在文件整理上花费的功夫。\n二、文件整理准则\n1. 目标\n核心目标：5-10s能找到自己需要文件。\n辅助目标：重要文件唾手可得、重要文件需备份、重要文件保留版本。\n2. 操作\n建立合适的文件结构\n建立自己的命名规范\n使用搜索查询文件\n定期整理文件\n3. 文件夹建立规范\n易于区分：每个文件夹功能不交叉，且名字易于区分。\n4. 文件建立规范\n精准：每个文件的命名要准确表达，文件的名称要详细、规范、避免重复与歧义。\n一致：文档内容的统一出口最初在产品这，至少在自己在存文档时要做到同一个项目的文件名称统一，不然按照关键字模糊搜索时也是很苦逼。\n三、文件分类\n在日常的工作中，个人会保存的文件主要分为如下几类。\n项目文件：一个项目从0-1的一揽子文件\n个人文件：个人述职、个人绩效、个人模板文件等文件\n产品文件：公司产品的接口文档、数据库设计文档\n日常文件：杂七杂八但和项目不挂钩或者关系不大的文件\n1. 项目文件\n说起项目文件，就需要说起一个项目的流程，简单来说项目可以分为前期准备、中期设计、后期总结，…",
          "link": "http://www.woshipm.com/pd/4867596.html",
          "publishedOn": "2021-07-14T11:12:47.000Z",
          "wordCount": 305,
          "title": "【规范】让你终生受益的文件整理"
        },
        {
          "id": "http://www.woshipm.com/it/4866588.html",
          "author": "网文航海家",
          "description": "编辑导语：在互联网的依托下，网文的发展蒸蒸日上。同样地，网文的IP和社会价值是固定存在并增长的，网文出海工具也随之发展了起来。作者从各方面分析了网文出海的发展，与你分享。\n\n\n相信关注出海业务的朋友这几年陆续都看到了各大媒体对于网文出海的报道，这其中包括了CCTV13报道的《2020网络文学出海发展白皮书》、中国青年报的《中国网文出海外国人能懂也能写》。\n但90%的人对于网文出海的认知程度还比较浅，仅仅停留在媒体曝光的像阅文集团这种“中国网文天团”的出海新闻上。话不多说，小编作为网文航海家的编辑及交付团体中的一员，通过实战网文的服务经验和大量的案例分析，先给大家分享关于网文出海的干货。\n一、中国移动互联网出海的历程\n2013年到2014年，工具类应用出海；\n2015年，移动游戏出海规模化，工具类应用形成规模；\n2017年至今，本地化出海的游戏、直播、短视频、电商已经在东南亚、中东、非洲、欧洲、美国等地区遍地开花。\n但国外各区域市场的现实情况千差万别，网络、物流、支付等基础设施并没有像国内一样完善，如何保持业务的持续增长是摆在所有电商出海创业者面前的一道难题。\n\n2021年6月4号“巅峰期400亿跨境电商巨头环球易购被申请破产”。\n无数的跨境电商韭菜在短视频线上线下课程上被反复收割，如今的跨境电商、游戏出海依然有很多机会但已然不再是蓝海。\n随着在线阅读习惯的养成，以及版权运营的逐步成熟，我国网络文学市场规模保持较快的增长。\n2019年我国网络文学市场规模为195.1亿元，同比增长27.1%；2020年我国网络文学市场规模为238.9亿元，同比增长22.5%。在市场持续向好的环境下，未来我国网络文学市场规模将持续增长。\n\n从用户规模来看，网络文学用户规模逐年增加。\n2018年我国网络文学用户规模为4.3亿人，同比增长13.2%；2019年我国网络文学用户规模为4.6亿人，同比增…",
          "link": "http://www.woshipm.com/operate/4866588.html",
          "publishedOn": "2021-07-14T11:02:45.000Z",
          "wordCount": 311,
          "title": "2021网文出海操作手日记：寻找正确姿势"
        },
        {
          "id": "http://www.woshipm.com/?p=4866813",
          "author": "SAAS老司机",
          "description": "编辑导语：在做SaaS产品时，我们经常会收到客户的一些埋怨，尽管我们做的已经够努力了，但还是逃不过客户的追问。对于这样的情况，我们该如何应对呢？\n\n\n“这个不应该是你们帮我全部弄好的吗？”\n“买完之后怎么就不理人了？”\n“你们当时销售不是这样说的啊？”\n“我要找你们X总反馈。”\n这些话对于一个服务从业者来说，再熟悉不过，尤其是对于SaaS产品来从业者来说，简直“余音绕梁，三日不觉”，客户行业素质稍微差一点的，甚至直接口吐芬芳（做客户成功太难了）。\n为什么客户会有这么大的反差？我明明已经很努力了，到底怎么样客户才会满意？什么样的客户服务算好的服务？\n我相信这些问号大家或多或少都有思考过、讨论过，或者更切确地说，相互吐槽过。\n想不清楚，就做不明白。所以我们试着剖析一下事情的本质——是什么、为什么、从哪里来到哪里去。\n一、SaaS产品的客户服务是什么？\n客户服务，度娘给出的解释是：主要体现了一种以客户满意为导向的价值观，它整合及管理在预先设定的最优成本——服务组合中的客户界面的所有要素。\n讲的比较虚，解释一下，就是为了让客户满意的一种方式。我们一般提到服务，就会联想到海底捞的服务，五星级酒店的服务，这些指的一般都是人工的服务。\n那么对于SaaS产品而言，客户服务也是听过人工达到客户满意的价值观吗？\n我认为，对于客户感知来说，只要不是实物产品，其他的都是服务，所以我认为SaaS本质上就是一种服务，是通过“软件+人工服务”方式实现的一种产品，也就是说产品也是实现服务的一种重要载体。\n对于SaaS公司来说，服务是实现SaaS商业模式的重要途径，只有把客户服务好了，客户才会续费，才会转介绍增购，才会带来更多的商业价值。\n二、为什么要做好客户服务？\n那是不是一定要提供提供人工服务？只提供软件服务行不行？像某鹅就一直没有人工服务。\n也不是不行，我们一直讲，好的产品是不需要服务的，只要产品足够…",
          "link": "http://www.woshipm.com/pd/4866813.html",
          "publishedOn": "2021-07-14T10:17:47.000Z",
          "wordCount": 292,
          "title": "客户成功实战笔记（10）：长期有耐心做好客户服务"
        },
        {
          "id": "http://www.woshipm.com/it/4871353.html",
          "author": "Anne",
          "description": "编辑导语：曾经一夜暴富的“信小呆”现在怎么样了？锦鲤热潮的掀起让许多人将希望投射至“锦鲤”身上，然而寄托于“锦鲤”似乎并不能让我们过上无忧的生活，我们的生活仍旧被消费主义浪潮裹挟着。也许，当下我们更应该做的，是专注自身。\n\n\n近一个月的热点有点多，但有一条消息冲上微博热搜后并没有引起人们多大关注：3年前的亿元支付宝锦鲤信小呆，在昙花一现后淡出人们视野，突然又自曝“生活不如意”。\n根据她的自述，为了用完支付宝送出的旅游优惠券，她先辞去了工作，后花光了20多万积蓄，现已回不到原先的生活轨迹。\n对此，有人质疑她这次卖惨是又一次营销。\n从“打工人”一夜变成“中国锦鲤”的信小呆，曾为了领“价值1亿”的支付宝奖品，花光20万积蓄、累到病倒。而之后也并没有过上人们想象的那种生活，反而被流量裹挟，充满了更多迷茫。\n她的遭遇看似与我们无关，但其实暗含着一个让很多人深陷其中的现象：我们有时消费的东西已经远远超出所需要的，但我们还不得不接受，并为此疲于奔命。消费主义给人带来的所谓绚烂，最终都会用更多空虚和迷茫来偿还。\n一、三百万分之一的概率\n2013年7月13日，一条来自账号“锦鲤大王”的“关注并转我子孙锦鲤图者，一月内必有好事发生”的微博一夜爆红，这条微博配上了一张锦鲤人鱼在池塘里游泳的画像，而直到现在这条微博仍在被转发，几乎每日都会有人在评论区“还愿”。\n\n截至目前，该条微博转发量已高达一千余万，评论量早已破百万。\n而该账号粉丝量达2162万，其同名淘宝店铺主打转运手链、转运耳钉等饰品，粉丝订阅量已过20万。在销量最高的一条手链提问区里，一名买家迫切地问着：“有转运的吗”？\n然而，据史学家查考，这些通常在互联网上象征着“好运”和“心想事成”的锦鲤并非发源于中国。而是来自日本的“红白锦鲤”品种。这种锦鲤由于基因变异，在200多年前的日本被偶然被人注意到并饲养。直到1880年左右，红白锦鲤在日本…",
          "link": "http://www.woshipm.com/it/4871353.html",
          "publishedOn": "2021-07-14T10:11:09.000Z",
          "wordCount": 374,
          "title": "被阿里选中的“中国锦鲤”，病了"
        },
        {
          "id": "http://www.woshipm.com/it/4866004.html",
          "author": "卡思数据",
          "description": "编辑导语：抖音和快手纷纷将重点放在社交上，无论是短视频创作也好，还是近期抖音的“同城圈子”的社交功能，都在将社交做大。抖音、快手逐梦社交，究竟是为了什么？\n\n\n微信的不完美，和短视频日益增长的活跃用户数和使用时长，让抖音、快手为代表的视频社交平台，从未放弃过对社交流量的狂热追寻。\n但相比于前两年，平台们试图通过独立社交软件来撕开微信入口、挺进社交腹地有所不同，现在的抖音和快手，部署和完善社交产品功能的愿望或许更为朴素。\n短期看，更多是希望通过社交来提升用户在平台内停留时长，并通过社交关系沉淀以及社区信任度提升，来助力直播、电商、本地生活、游戏等业务增长。\n但这条路依然不好走！\n一、逐梦社交：抖、快都做了什么？\n据Tech星球前日报道，抖音正在测试了一个名为“同城圈子”的社交功能。\n该圈子定位是同城兴趣圈，旨在帮助本地用户在特定的兴趣圈子中进行交流和交友，而从入口上看，同城圈子位于同城界面，与抖音地图并列，而如果要加入圈子，则需要回答问题或者拍摄与圈子内容相符的短视频，以提升普通用户进入圈子的门槛，并丰富刚起步圈子的内容形态。\n\n这已是抖音第N次围绕社交有新动作了！\n从今年起，抖音明显加快了平台内社交产品建设，似乎每一个月，都会有相关的社交产品上线或进入到测试阶段。而卡思近来所关注到的抖音社交动作，每每都与罗永浩老师有关。\n一是今年3月，抖音将粉丝群聊功能调整到了账号主页，直接显示在“商品橱窗”旁边。\n该操作一经发生，就受到了“交个朋友”团队的积极使用，仅3天的时间，薅了50个粉丝群（主页只显示5个），进群的用户将在第一时间收到罗老师的短视频、直播动态。\n此外，群内也支持各种活动玩法，如：红包、连线、表情包等激活群成员之间的互动。\n\n另外一个是在4月，抖音启动“朋友聊天室”功能内测，互关好友及受邀请的朋友可一起参与聊天，类似的KTV功能也已于今年2月开始测试。\n4月1日，罗永…",
          "link": "http://www.woshipm.com/it/4866004.html",
          "publishedOn": "2021-07-14T10:00:58.000Z",
          "wordCount": 277,
          "title": "逐梦「社交」，抖、快图什么？"
        },
        {
          "id": "http://www.woshipm.com/?p=4866468",
          "author": "刘志刚",
          "description": "编辑导读：即便是在移动互联网如此发达的今天，PC端用户的月活规模仍然有超过5亿。从巨头们的布局不难看出，PC端受到的关注也越来越多。这是不是意味着，互联网商业的底层逻辑变了？本文作者对此进行了分析，与你分享。\n\n\n最近一段时间，互联网行业出现一些颇有意思的现象。\n移动时代的后起之秀抖音推出了网页版；微软发布的Windows11兼容安卓；微信PC版客户端更新了搜一搜，新增了公众号、小程序、新闻、表情、朋友圈、视频等内容，更像是一个嵌在微信内的搜索网站。\n大人，时代又变回去了？\n把这些碎片化的信息组合到一起，再联想到如今的互联网“内卷”越来越严重，对于各家在PC端最新的动作也不难找到一个解释：流量大盘增长停滞的背景下，PC端似乎又回到了巨头们的视野中。\n一、互联网商业底层逻辑：入口决定价值下限，技术决定价值上限\n如果单纯的从流量的角度来看，根据艾瑞数据显示，即便是在移动互联网如此发达的今天，PC端用户的月活规模仍然有超过5亿。虽然相比如今互联网巨头们动不动7、8亿的总流量池是少了一些，但也算是一个不小的流量规模。\n这可能也是抖音、快手推出网页版背后的原因，对移动时代的“后起之秀”们来说，PC流量价值仍然有待挖掘。\n实际上，移动互联网时代，PC端的价值可能不仅仅在于流量，更多的可能在于入口的价值，比如，网页版短视频网站可能会演变成长视频网站，去跨越边界式的争夺更多的用户时长。这时PC更多的是一个入口，是一个扩张的机会。\n对于PC端入口价值体现的较为明显的，是那些PC时代诞生，移动时代进一步转型发展的互联网企业。不少PC时代的互联网企业虽然转型较晚，但也有很多较为成功的例子。比如百度、金山、360等企业，核心在于各自抓住了一个关键入口。\n实际上，移动互联网时代，很多PC互联网时代的商业内核都很好的延续了下来，比如说流量变现，服务订阅等，一些核心的商业反而在移动时代得到了新的诠释。\n…",
          "link": "http://www.woshipm.com/it/4866468.html",
          "publishedOn": "2021-07-14T09:58:33.000Z",
          "wordCount": 260,
          "title": "互联网商业底层迭代：“流量分发”到“数据分发”"
        },
        {
          "id": "http://www.woshipm.com/?p=4865718",
          "author": "ADSCOPE",
          "description": "编辑导语：做APP广告流量变现的小伙伴，一定想知道一个百万日活的APP能够有多少广告收入吧？毕竟知彼，才更有动力朝着目标努力。作者为我们盘点了一个百万日活APP的广告收入方式，我们一起来看看吧。\n\n\n6月份，AdScope联合蝉大师举办了一场“APP流量变现技巧”线上分享交流会，私下里就有小伙伴问了：“我们DAU如果能达到百万，广告一天能有多少收入……”\n想必这应该是每个想做APP流量变现的小伙伴最想知道的问题了。今天就来跟大家算算——一个百万日活的APP，一天的广告收入有多少？\n首先，我们来看看百万DAU在总体APP榜单中处在一个什么位置：\n根据极光大数据发布的《极光数据：2021年Q1季度移动互联网行业数据研究报告》DAU飙升榜中，今日水印相机DAU 123.7万，最为接近我们说的百万DAU APP。\n\n然后，我们再看看今日水印相机在App Store中的排名：\n\n（数据来源：蝉大师App Store中国区市场实时榜单2021.7.12 15:00）\n今日水印相机在应用总榜中排名209位，摄影与录像类别中排名23，总榜排名246，由此，我们可以看出百万DAU其实已经算是比较知名的APP，用户量、粘性、知名度都已经处在较高的水平，如果进行广告变现收入已经很可观。\n那么回到我们前面标题上的问题，一个百万DAU的APP，一天的广告收益具体能到多少？\n这与APP每日产生的可用于变现的流量量级有关，也与APP的流量溢价能力相关，流量量级跟用户量、用户频次、广告位数量、位置和形式等因素相关，而流量溢价能力则跟APP的品牌营销价值有关。\n除此之外，更为重要的是采取什么形式售卖广告，因为不同类型的广告售卖所取得的收益存在着明显差异。\n一般达到百万DAU的APP知名度较高、用户营销价值较大，品牌溢价能力较强的话，会采取品牌方式售卖，优质优价，获得最大收益。\n优质广告位流量按天/时间段售卖…",
          "link": "http://www.woshipm.com/pd/4865718.html",
          "publishedOn": "2021-07-14T09:47:21.000Z",
          "wordCount": 242,
          "title": "一个百万日活的APP，一天广告收入到底有多少"
        }
      ]
    },
    {
      "title": "PMCAFF互联网产品社区 - 产品经理人气组织",
      "feedUrl": "https://api.pmcaff.com/api/v0/select/rss",
      "siteUrl": "https://www.pmcaff.com",
      "articles": [
        {
          "id": "https://coffee.pmcaff.com/article/zNBrYXGPQe",
          "author": null,
          "description": "​现代经济学理论认为，企业本质上是“一种资源配置的机制”，其能够实现整个社会经济资源的优化配置，降低整个社会的“交易成本”。\n\n权限管理系统的本质是企业内部或企业之间的资源在B端产品上以特定机制配置的映射；所以权限管理系统的贴身情况也是衡量产品商业模式好坏、用户价值高低的一杆标尺。\n权限管理系统的设计中常遇到的问题有：\n\n配置不规范，系统基础不稳，拓展性差；\n\n配置不灵活，用户需求难满足，体验差；\n\n配置太灵活，逻辑会复杂，实施成本高；\n\n那么，如何设计一款贴身并能随着产品一起生长的权限管理系统呢？\n在古代，没有互联网、没有软件时，泱泱中华在中央集权的帝制制度、“君君臣臣、父父子子”的角色说明书等管理系统中正常运转；皇帝把资源下发给特定的人、岗位角色、宦官集团等以促进农业生产、税收、户籍管理、治安维护等；资源包括权力、办事流程等抽象资源，也包括钱财、粮食、盐、矿等实物资源，同时包括印章、信纸、官服、轿子、马等承载资源、象征权力、代表等级的工具。而管理机制除了帝制和角色说明书，还有子承父业的继承机制、藩王行为规范、文官武官的互斥监督、官职逐级递升约束、虎符口令双向验证等等；在盛世时期百姓人口增加、战争时期军队数量增加要在基础机制上做适应性的调整。\n权限管理的本质也大致如此，管理的是主体对客体遵循特定机制做出的行为。\n\n权限管理系统的组成要素有哪些？\n常见的权限模型有哪些？\nOracle和Salesforce的权限模型是啥样的？\n实操案例中如何应用的？\n有哪些经验及建议？\n\n一、4个基本要素\n权限是主体对客体遵循特定机制做出的行为。所以，权限的4个基本要素就是主体、客体、行为、机制。\n1.1、主体\n指行为的行使者，是操作的发起者。主体的类型有很多种，常见的有：\n\n用户及用户组。更准确地术语应是“系统使用者”，其与系统的账号体系相对应，一个用户对应一个唯一账号；多个用户组成一个用…",
          "link": "https://coffee.pmcaff.com/article/zNBrYXGPQe",
          "publishedOn": "2021-07-11T14:33:19.000Z",
          "wordCount": 94,
          "title": "B端产品如何设计权限系统？4要素-5模型-2特殊-1案例-2建议"
        },
        {
          "id": "https://coffee.pmcaff.com/article/a1LRb8ylLZ",
          "author": null,
          "description": "序\n上半部分文章主要围绕指标，包括选定关键指标（主要指标VS次要指标），从关键结果指标拆解出过程指标，并定下阶段性目标。这些是数据分析的基础工作，在没有做好之前，不建议直接就开始做功能、打点取数等等。如果这部分已经做好了，那么可以看接下来的文章（没有的话建议戳上半篇）。\n接下来讲一下有了指标之后到底怎么去设计打点和实验，包括怎么分析数据结果、怎么作出直观的图表和指标的持续监控，还是比较实用的技能。 学姐会配合超多实用的案例，尽可能讲得清晰一些，帮大家排雷避坑。\n\n一、打点详解\n打点和实验是同步设计的，因为这两者会互相影响。有些童鞋对DAU、交易额、转化率等大指标监控比较重视，但是拆分到某个页面、某个功能的打点就设计得大条了一些，导致经常要等数据结果出来了，才发现还需要补一些打点。所谓巧妇难为无米之炊，如果打点没打好，连数据源都没有，数据分析能力再强也没用。\n打点分为前端（客户端）打点和后端（服务端）打点两种。\n\n先介绍常用的前端打点，这类打点主要是用来记录用户行为的，也就是当用户和你的页面产生了交互之后（比如点击了某个按钮或者打开了某个页面），本地产生一条包含很多字段的信息（相当于xls的一行），等到一定的时间之后上传到服务器上，然后通过数据清洗、入库等等，就能提取出来进行数据分析了。\n前端打点必须包含的字段类型（相当于xls的表头）有以下三大类：\n基础信息：比如用户的渠道、平台、操作系统、手机型号、用户身份唯一标识（uuid、token）、页面id等等，以便后续做一些基本的分析。也可以再进一步，根据业务特性加上一些字段：比如一个LBS的App可以把城市、经纬度也加到基础信息中，比如一个交易平台可以把用户浏览商品的sku id或下单的order id带上，只要用户有和商品id、下单相关的操作，这两个字段就都可以记录上。这么做的好处是不需要产品/运营每次额外提需求，默认每条打…",
          "link": "https://coffee.pmcaff.com/article/a1LRb8ylLZ",
          "publishedOn": "2021-06-29T02:56:49.000Z",
          "wordCount": 104,
          "title": "十年大厂产品的数据分析宝典（下）：数据打点、分析、做图表、监控的实用技巧"
        },
        {
          "id": "https://coffee.pmcaff.com/article/Oak7DN23LJ",
          "author": null,
          "description": "各位小伙伴好，本文是电商后台设计系列文章的第二篇，库存模块。关于第一部分商品模块的内容可以查看我之前的文章。\n\n一、库存基本概念\n1. 库存定义\n首先我们来了解一下库存的基本概念，狭义上，库存指仓库里实际存储的货物，为了满足未来需要而准备的储备资源。包括在仓库里的、在实体店里的、在运输途中，包括在外的所有商品。库存代表企业对于商品实物的把控能力。而在电商系统中，库存是虚拟数字，决定了销售端的供给。\n\n仓库\n那么，我们为什么要研究与管理好库存呢？换句话说，库存管理不当会带来的危害有哪些。通常，我们会认为库存管理不当有两种情况：库存过少、库存过大。\n\n库存过少的风险：产生缺货，损失营业额进而损失利润。\n\n库存过大的风险：商品因变旧、变质、过期而产生损耗；占用库存且增大资金压力。\n\n因此，库存即成本，亦是业务筹码。库存管理能力代表供应链管理水平。\n2. 库存变动\n库存是一个动态变化的数字，接下来我们来探究一下库存的变动过程。首先我们了解几个库存的概念：\n\n销售库存：可以售卖的商品数量。\n\n实物库存：仓库存放的实物商品数量。\n\n可用库存：可以对外销售的数量。\n\n锁定库存：已经被预定的商品数量。\n\n已售库存：已经出售的商品数量。\n\n活动库存：做促销活动时设置的库存，可以共享普通库存也可设置独立库存。\n\n预售库存：做预售活动时设置的虚拟库存，预售订单需支付尾款订单才能成立\n\n接下来我们看一下几个引发库存变动的基础操作：\n\n增加：手动调整或实时同步（与实物库存系统打通）。\n\n锁定：下单之后锁定库存。\n\n解锁：订单取消之后释放锁定库存。\n\n扣减：订单支付成功之后扣减库存，扣减锁定库存。\n\n返还：退货、换货后返还库存，相当于增加库存。\n\n异常处理：库存数据在定期校验时，如果出现异常数据，就需要进行异常处理（自动或人工处理）\n\n在库存的变动中，最关键的节点是库存的扣减，在什么时候扣减库存非常重…",
          "link": "https://coffee.pmcaff.com/article/Oak7DN23LJ",
          "publishedOn": "2021-06-28T02:26:16.000Z",
          "wordCount": 85,
          "title": "5000字干货：产品经理必学之电商后台设计—库存模块"
        },
        {
          "id": "https://coffee.pmcaff.com/article/a1LRb82oLZ",
          "author": null,
          "description": "欢迎关注公众号：薛慧卿。\n​前言\n憋了很久，终于打算开始切入这个话题了。最近一直在思考，伴随着拉新成本越来越高，对于以视频为载体的内容平台而言，就需要更加细致的为新用户提供起到留存价值的内容，将新用户有效的激活、留存，让自己少花一些冤枉钱。因此，新用户冷启动内容推荐变成为“拉新内卷”时代的重要议题。\n\n\n通常意义下，我们所说的视频行业有按视频时长划分的如长视频、短视频还是最近奇奇怪怪硬炒作的“中视频”，也有按照版权形式进行划分如PPC（版权采买）、PGC（平台分成）、UGC等。本文更希望将目前的市面上的视频内容性质拆分为版权视频（采买或分成）、用户视频两种视频形式。\n\n一、版权视频和用户视频内容差异\n\n1.1内容成本\n\n众所周知，国内版权采买目前是一个非常昂贵的状态，因此内容数量和平台资金呈现正相关。用户视频目前除了大多头部MCN及创作者之外，绝大多数视频都是免费状态，当然也存在视频平台补贴所有创作者的状态出现。因此从内容成本而言，版权视频内容成本远高于用户视频。\n\n1.2内容体量\n\n这里的内容体量包含两个方面：数量及多样性。\n\n先说数量，版权视频中的每一个内容都是通过花重金采买的，因此从供给端的资金成本而言，头部PPC、PGC平台内容数量就会低于UGC视频平台。\n\n再说多样性，版权视频从制作到上线，大体流程是制片人选择ip-编剧编撰-剧本敲定-导演引入及选角-内容拍摄-剪辑-送检审核-上线8大步骤。用户视频的诞生主要步骤是有创意-拍摄（剪辑）-安全审核-上线这4大步骤。通过以上步骤我们可以发现每一步都是在降低内容多样性，版权视频需要8大步骤，而用户视频仅需要4大步骤。因此在内容多样性方面看，用户视频的多样性大幅领先版权视频。\n\n1.3内容质量\n\n可以延续1.2的视频漏斗模型，通常而言，经过步骤越多，审核人员和制作人员专业性越强，对于内容质量的把控也更高，专业制作水平也更强…",
          "link": "https://coffee.pmcaff.com/article/a1LRb82oLZ",
          "publishedOn": "2021-06-28T02:13:29.000Z",
          "wordCount": 82,
          "title": "视频场景下新用户的内容推荐策略"
        },
        {
          "id": "https://coffee.pmcaff.com/article/oyLPllqqLA",
          "author": null,
          "description": "这是我之前好友总结整理的APP版本迭代流程与规范，主要涉及到版本迭代过程中的规范流程以及涉及到版本各个角色的职责分工等内容。\n为了避免和团队成员撕逼扯皮，可以按照如下规范流程和团队成员宣导，落实每个环节各个角色的职责和内容，保证每个环节都能高效协作，避免踩到坑里，相关干货流程分享给大家。\n本文目录如下：\n一、引言\n\n二、需求汇总阶段流程\n三、需求评审阶段流程\n\n四、需求开发&测试阶段流程\n五、内测阶段流程\n六、APP版本号命名规则\n1、引言\n1.1、目的\n基于现在的开发流程中缺少的环节进行补足，使得开发流程更加的流畅和正规化，以便以后的查阅与归档使用。面对互联网行业中激烈的竞争，让我们的开发流程更完整、更有效率，产品才能脱颖而出。\n1.2、范围\n本文档适用于App产品的迭代研发，主要流程包括：需求汇总、需求评审、技术&用例评审、开发&测试排期、开发&测试、内测体验等环节。以后的产品开发流程也可以参考此文档的环节进行开发。\n1.3 、读者对象\n本文档的目标读者对象主要包括：\n产品经理：输出&收集汇总每个版本迭代的需求，同时对App迭代进行体验验收，需求汇总阶段、需求评审阶段、内测体验阶段的主要负责人。\n交互设计师：根据相关需求文档，进行交互优化，输出优化原型图，提升产品整体用户体验。\n视觉设计师：根据需求文档&交互原型图作为视觉设计的步骤和资源产出的依据。\n项目经理：组织发起需求评审，并跟进评审结果及输出开发测试排期，需求评审阶段、发布上线阶段的主要负责人。\n开发：主导发起部分复杂需求的技术评审，根据需求文档编写代码，开发测试过程由版本经理主导推进，为迭代上线负责。\n测试：根据需求文档设计相关测试用例，并主导发起用例评审，跟进测试阶段的Bug解决。\n1.4、App迭代阶段流程图\n\n（点击查看大图）\n2、需求汇总阶段\n\n（点击查看大图）\n阶段推进方：主要由产品主导推进与收尾\n产…",
          "link": "https://coffee.pmcaff.com/article/oyLPllqqLA",
          "publishedOn": "2021-06-23T04:26:51.000Z",
          "wordCount": 174,
          "title": "5000字干货好文：APP版本迭代如何避免踩坑（建议收藏）"
        },
        {
          "id": "https://coffee.pmcaff.com/article/epk03DoaBy",
          "author": null,
          "description": "开篇\n先看看网易云音乐的发展历程：\n\n\n\n\n再来看看网易云音乐获得的成就：\n\n\n成功不可复制，是说成功没有唯一要素，而不是成功案例不值得研究。\n一款成功产品的背后，一定存在某种关键因素，或赶上了风口，或有雄厚的资本，或精准地把握了市场需求，但无论什么原因，这款产品一定有值得我们学习探究的地方。\n网易云音乐就是这样一款值得我们细细分析的产品：网易云音乐于2013年上线，在头部竞品占领了80%市场份额的情况下，仍然能从集中度很高的市场撕开一道口子，用了4年时间收获3亿用户，7年时间进入行业top3。\n音乐行业是有很长历史的传统行业，从CD时代，到MP3，再到PC客户端和移动端，中间有好几十年的时间。我们不禁会思考，网易云音乐是如何在一个线下成熟且行业环节复杂，线上竞争激烈的市场中脱颖而出的？\n得益于网易云音乐背后的关键人物——王诗沐，出版了《幕后产品》一书，使我们能够近距离地了解网易云音乐的发展过程，同时有机会结合实际案例学习优秀产品人王诗沐的产品心得。\n带着问题去找答案，更容易学有所得。所以，本篇文章会采用问题+答案的形式展开，enjoy~\n\n\n如何分析行业？\n要分析一个行业，先要搞清楚以下几个问题：\n\n这个行业有哪些玩家？他们之间的关系是怎样的？\n\n未来几年，这个行业会发生什么变化？在这些变化中会产生什么机会？\n\n面对这些机会，行业里的玩家可能会有什么动作？\n\n这个市场的相关市场是什么？它的上下游有哪些？谁是平台，谁是应用？\n\n这是一个零和市场吗？有没有办法做非零和市场？\n\n这个市场未来的变化是怎样的？应该如何抓住机会？\n\n（PS：这里的行业指的是一个完整的生产链条上的所有内容，而市场指的是链条中的某一部分）\n网易云音乐的成功，依靠的是音乐+社交的定位，而这些判断主要来自王诗沐对音乐行业的观察和分析，推断了由传统CD音乐转变到数字化音乐过程中可能产生的变化和机会：听音乐的需…",
          "link": "https://coffee.pmcaff.com/article/epk03DoaBy",
          "publishedOn": "2021-06-16T03:59:38.000Z",
          "wordCount": 89,
          "title": "从网易云音乐看产品设计"
        },
        {
          "id": "https://coffee.pmcaff.com/article/xqB6V909B4",
          "author": null,
          "description": "在上一篇文章，我们已经介绍了什么是埋点，以及如何选择具体埋点方式、位置。具体可点击查看 《什么是埋点？》\n埋点的前期知识背景了解的差不多了，接下来需要怎么拆解出埋点的需求，输出可行性方案给到开发呢？这篇文章，将会拆解6个步骤给到大家参考，还是那句话，具体的实施需要根据实际情况进行调整。这里说的不一定全对，但思路是可以参考的。废话不多说，请继续接着往下看吧。\n第一步：需求收集分析\n做埋点需求的第一步，是要理解埋点的具体价值和需求场景。我们要对需求进行梳理。首先要明确我们要分析什么样的场景，解决什么业务问题，要解决这个业务问题，要看什么样的数据，所以明确清晰产品的脉络和架构是关键。这里需要输出【产品信息结构图】【产品功能结构图】\n有了基础的梳理后，我们需要再将核心业务流程或页面流程梳理出来。将用户与系统的交互故事完整的梳理出来。这些都是决定了用户在使用产品时的任务路径，借助它，可以知道流程中的潜在地雷是什么，哪里的效率比较低，有助于全局化思考。后续我们就可以在每个流程步骤，考虑好用户的目的、场景，提炼出重要指标。这里需要输出【核心业务流程图】\n其实这里说的几个流程图，我们前期做别的需求分析时候可能梳理过了，也可以复盘一下即可。这里主要目的是了解需求背景目的，方便接下来的指标拆解。\n【案例分享】\n背景：\n我们做的产品是在线旅游产品预订平台，目前公司在组织架构调整的大背景下，为了跟公司其他业务部门整合，我们不再侧重点在app上，改为H5端，所以之前的业务需要迁移到H5上面，埋点需要重新埋。\n根据步骤一，我们拆解出【产品信息结构图】【产品功能结构图】【核心业务流程图】\n1.1【产品功能结构图】\n\n1.2【产品信息结构图】\n\n1.3【核心业务流程图】\n我们的核心业务流程，就是酒店的预订流程：\n\n第二步：设计指标\n不同的业务角色关注不同的数据指标。例如产品、运营关心的指标是不一样的。在设…",
          "link": "https://coffee.pmcaff.com/article/xqB6V909B4",
          "publishedOn": "2021-06-16T01:55:10.000Z",
          "wordCount": 84,
          "title": "Part 2 如何进行埋点（内附埋点文档模板）"
        }
      ]
    },
    {
      "title": "异次元软件世界",
      "feedUrl": "http://feed.iplaysoft.com/",
      "siteUrl": "https://www.iplaysoft.com",
      "articles": [
        {
          "id": "https://www.iplaysoft.com/?p=5518",
          "author": "X-Force",
          "description": "虽然在 Windows 下有着 Listary、Everything 等搜索神器，可以极快地根据“文件名称”来搜索和定位文件，但它们都缺少一个非常重要的功能——全文内容搜索。\nTextSeek 是一款支持 Win / Mac / Linux 的专业文件全文搜索工具。它与 Listary 等基于文件名搜索工具不同，TextSeek 除能按文件名来搜索指定目录外，还能支持无索引「搜索文件里的全部文字内容」，支持格式包括 PDF、Office (Word、Excel、PPT)、RTF，WPS 等常见文档……\n「 前往查看原文.... 」\n异次元还有这些值得一看：\n\nAnyTXT Searcher 免费全文搜索工具神器 - 速度超快查找文档内容 (类似 Everything)\ntagLyst Next - 让我们用更科学更智能的“标签”来分类整理文件吧！\nDocFetcher - 免费桌面文档全文搜索引擎工具，直接查找文档的全部文字内容！\nMarginNote - 颠覆学习方式的 iPad Mac 读书阅读笔记工具 (思维导图/知识整理)\n\n异次元正版数字商城  |  异次元首页  |  微信公众号  |  iPcFun  |  关注微博  |  软件精选",
          "link": "https://www.iplaysoft.com/textseek.html",
          "publishedOn": "2021-07-13T16:09:32.000Z",
          "wordCount": 511,
          "title": "TextSeek - 桌面全文搜索引擎工具，像百度一样搜索硬盘文件内容 (Win / Mac)"
        },
        {
          "id": "https://www.iplaysoft.com/?post_type=free&p=3980",
          "author": "X-Force",
          "description": "GoodSync 是一款非常优秀老牌的文件同步/文件备份工具软件，可以轻松将文件同步到硬盘、外接硬盘、云端网盘等存储空间中，让你的数据进行自动的备份和整理。\n\n异次元在很早前就推荐过 GoodSync 了！尽管 GoodSync 的软件界面比较朴素，但其功能相当强大而且可靠。它能支持单向同步(备份)以及双向同…… \n「 前往查看原文....  |  更多限时免费 」\n\n异次元正版数字商城  |  异次元首页  |  微信公众号  |  iPcFun  |  关注微博  |  软件精选",
          "link": "https://www.iplaysoft.com/free/goodsync",
          "publishedOn": "2021-07-13T07:05:20.000Z",
          "wordCount": 974,
          "title": "[限时免费] GoodSync 11 - 优秀文件同步/数据备份软件 (支持移动硬盘FTP局域网等)"
        },
        {
          "id": "https://www.iplaysoft.com/?p=5516",
          "author": "X-Force",
          "description": "无论是办公还是日常生活中，我们都常遇到一些纸质文档、屏幕截图等想要扫描成电子版甚至“将文字复制”下来使用。这时，就需要用到 OCR 文字识别工具了。\n在众多扫描和 OCR 工具之中，「白描」可谓是脱颖而出，一跃成为了无数人首选推荐的跨平台 OCR 扫描识别文字神器！它支持手机、电脑和网页版，易用出色的体验加上高准确率的文字识别能力，再配上翻译、表格识别转 Excel、图片批量扫描识别等功能，使得它实用性满分……\n「 前往查看原文.... 」\n异次元还有这些值得一看：\n\nScanbot Pro - 更现代化的实用手机扫描仪应用\n扫描全能王 - 可能是最出色手机文档扫描工具，支持OCR文字识别\n扫描汪 - 免费离线的 iPhone 手机拍照文字识别应用 APP (不联网离线识别)\nScanner Pro - 最好的 iOS 手机扫描仪软件应用之一！支持中文 OCR 文字识别\n\n异次元正版数字商城  |  异次元首页  |  微信公众号  |  iPcFun  |  关注微博  |  软件精选",
          "link": "https://www.iplaysoft.com/baimiao.html",
          "publishedOn": "2021-07-11T04:58:47.000Z",
          "wordCount": 516,
          "title": "白描 APP - 抓取文字利器！免费好用的扫描 OCR 文字识别工具 (手机/电脑/网页跨平台)"
        },
        {
          "id": "https://www.iplaysoft.com/?post_type=news&p=5514",
          "author": "X-Force",
          "description": "阿里云盘自从上线开始就一直颇受用户关注，最重要的一点是它号称“永不限速”！如果你一直被「百度网盘」的龟速气炸，那么免费+不限速的阿里云盘可能就是最理想的替代品了。\n\n下载阿里云盘客户端\n阿里云盘在发布手机版、电脑版客户端之后，终于正式开放大家最需要的「网盘分享功能」了！…… \n「 前往查看原文.... 」\n\n异次元正版数字商城  |  异次元首页  |  微信公众号  |  iPcFun  |  关注微博  |  软件精选",
          "link": "https://www.iplaysoft.com/news/5514",
          "publishedOn": "2021-07-10T05:26:12.000Z",
          "wordCount": 363,
          "title": "阿里云盘正式开通“文件分享”功能，依然不限速！还用龟速百度么？"
        },
        {
          "id": "https://www.iplaysoft.com/?post_type=news&p=5513",
          "author": "X-Force",
          "description": "近日微软已经向预览体验计划的用户发布了 Windows 11 Build 22000.65 (第二个预览版) 更新（KB5004745），感兴趣的朋友可以下载新版使用了。\n\n「下载最新版 Windows 11 系统镜像」\n这是微软官方推出的 Windows 11 预览版第二次更新，改进的项目非常多。比如在开始菜单、Windows 设置的电源模式中添加了新的搜索栏…… \n「 前往查看原文.... 」\n\n异次元正版数字商城  |  异次元首页  |  微信公众号  |  iPcFun  |  关注微博  |  软件精选",
          "link": "https://www.iplaysoft.com/news/5513",
          "publishedOn": "2021-07-10T02:06:25.000Z",
          "wordCount": 449,
          "title": "Win11 Build 22000.65 第二个预览版发布 - 新版本变化内容汇总"
        },
        {
          "id": "https://www.iplaysoft.com/?p=5497",
          "author": "X-Force",
          "description": "在苹果发布了 macOS Monterey 系统之后，微软终于如约地正式发布了其最新一代的操作系统——Windows 11 了！并且微软还很厚道地宣布「Win11 可以完全免费升级」。\n新版的 Windows 11 系统相比 Win10 带来很多显著的变化，比如全新设计的“毛玻璃”界面、原生支持运行 Android 应用、窗口布局管理 / Widgets 小工具、新的应用商店、支持 XBox Game Pass 订阅、支持云游戏、DirectX 12、AutoHDR 等更强大的游戏体验……\n「 前往查看原文.... 」\n异次元还有这些值得一看：\n\nWindows 10 最新版本 21H1 正式版 ISO 镜像下载 (微软 MSDN / VL 官方原版系统)\nWindows7集成SP1补丁中文旗舰版光盘镜像下载 (真正微软MSDN官方原版32位+64位)\nWindows 8.1 官方中文正式版下载与免费在线升级更新方法 (微软MSDN原版ISO镜像)\nAll in One Runtimes - 快速一键安装全部 Windows 系统必备常用运行库合集\n\n异次元正版数字商城  |  异次元首页  |  微信公众号  |  iPcFun  |  关注微博  |  软件精选",
          "link": "https://www.iplaysoft.com/windows11.html",
          "publishedOn": "2021-07-09T19:36:31.000Z",
          "wordCount": 1168,
          "title": "Windows 11 最新系统 ISO 镜像下载 - 全新界面/可运行安卓应用/免费升级 (BT网盘地址)"
        },
        {
          "id": "https://www.iplaysoft.com/sumatra-pdf.html",
          "author": "X-Force",
          "description": "世界在进步，软件的体积和功能同时也在与日俱增。但是，「小巧、快速」依然是无数用户的挚爱，而日常用来查看文档的 PDF、ePub、Mobi 等电子书阅读器也同样如此。\nFoxit Reader (福昕阅读器)、PDF-XChange Viewer 等曾经抢占过体积庞大的 Adobe Acrobat Reader 的市场，可惜它们在商业化过程中，也渐失本来轻盈、免费的特点。而如果你需要一款真正小巧精悍的电子书阅读器，那么开源免费的 Sumatra PDF 绝对是不二之选……\n「 前往查看原文.... 」\n异次元还有这些值得一看：\n\nMarginNote - 颠覆学习方式的 iPad Mac 读书阅读笔记工具 (思维导图/知识整理)\nThief Book - 上班摸鱼偷偷看小说的利器 (伪装隐蔽看书工具/老板键隐藏)\nAdobe Acrobat Reader DC - 最出色的官方免费 PDF 文档阅读器！(字体清晰/速度快)\nFoxit Reader 福昕阅读器软件中文版下载 (好用快速免费，可制作创建PDF文档)\n\n异次元正版数字商城  |  异次元首页  |  微信公众号  |  iPcFun  |  关注微博  |  软件精选",
          "link": "https://www.iplaysoft.com/sumatra-pdf.html",
          "publishedOn": "2021-07-08T09:20:43.000Z",
          "wordCount": 760,
          "title": "Sumatra PDF - 真的轻快！免费开源小巧绿色电子书阅读器 (支持 ePub/Mobi/CBR 等)"
        },
        {
          "id": "https://www.iplaysoft.com/?p=5511",
          "author": "X-Force",
          "description": "随着日常生活中拍照片、录视频越来越多，我们对手机存储空间的要求也变得越来越高。但手机上寸土寸金的空间根本架不住保存每天不断增加的照片和视频。\n除了花钱购买「群晖」等 NAS 设备、iCloud 或各种网盘会员以外，我们其实还可以借助一些免费软件比如 Lomorage 来零成本打造一个属于自己的私有相册云存储！帮我们快速方便地将手机上的照片视频自动上传备份到电脑 / 树莓派 / 服务器等地方去……\n「 前往查看原文.... 」\n异次元还有这些值得一看：\n\n微软照片伴侣 Photos Companion - 无线发送手机照片视频到电脑 Win10 PC\n扫扫传 ScanTransfer - 免装APP！扫码即可将手机照片视频无线传输到电脑上\n彩色气球 - Facebook 推出“中国版”免费无限空间云相册 / 手机照片备份APP\nNextcloud - 搭建个人专属或团队共享的私有云同步网盘 (开源免费跨平台)\n\n异次元正版数字商城  |  异次元首页  |  微信公众号  |  iPcFun  |  关注微博  |  软件精选",
          "link": "https://www.iplaysoft.com/lomorage.html",
          "publishedOn": "2021-07-05T04:20:07.000Z",
          "wordCount": 586,
          "title": "Lomorage 免费无限制的私有相册云 - 手机照片视频自动备份到电脑/服务器/树莓派等"
        },
        {
          "id": "https://www.iplaysoft.com/?p=5509",
          "author": "X-Force",
          "description": "最近大家都被 Windows 11 和 macOS Monterey、iOS 15 等新推出的操作系统刷屏了。其实除了这些，还有一个相当让人振奋的 NAS 系统发布了——群晖 DSM 7.0 正式版。\n尽管不是通用操作系统，但群晖 (Synology) 在 NAS 界的影响力还是能比肩苹果、微软的。群晖 NAS 之所以在定价比同行高的情况下，依然成为市场上销量和口碑双赢的产品，它的这套 DSM 系统可谓功不可没！无数人花精力搞“黑群晖”，也是看中了 DSM 配套软件好用……\n「 前往查看原文.... 」\n异次元还有这些值得一看：\n\nNextcloud - 搭建个人专属或团队共享的私有云同步网盘 (开源免费跨平台)\n群晖 DS412+ NAS 网络存储器详尽功能应用评测，值得你拥有的智能专属数据中心云存储！\n微力同步 - 跨平台文件同步软件 Resilio Sync 替代品 (电脑/手机/NAS)\nSyncthing - 免费开源替代 Resilio / BT Sync 的文件夹同步工具神器 (搭建同步网盘)\n\n异次元正版数字商城  |  异次元首页  |  微信公众号  |  iPcFun  |  关注微博  |  软件精选",
          "link": "https://www.iplaysoft.com/synology-dsm.html",
          "publishedOn": "2021-07-02T03:21:05.000Z",
          "wordCount": 820,
          "title": "群晖 DSM 7.0 正式版固件发布下载 - 玩腻了 Win11 来升级 NAS 操作系统吧"
        },
        {
          "id": "https://www.iplaysoft.com/?p=5493",
          "author": "X-Force",
          "description": "苹果发布了最新 iOS 15、iPadOS 固件，同时新款 Mac 也已采用 Apple 自研处理器，最新的 macOS Monterey 系统不仅肩负着架构过渡的使命，同时还要面对 Windows 11 的冲击。\n最新的 macOS Monterey 12.0 公测版 同样给 Mac 带来很多新功能，比如能让 iPad 和 Mac 共用键盘鼠标操控的“通用控制”、图片照片实时识别文字、Safari 改进、SharePlay 与朋友看剧听歌、专注模式、捷径 for Mac、接收 AirPlay 投屏等；而且在 M1 处理器上，还能直接在 Mac 上运行 iOS 应用……\n「 前往查看原文.... 」\n异次元还有这些值得一看：\n\n苹果 macOS Big Sur 最新官方正式版下载 / Mac 11.0 操作系统 dmg 镜像\n苹果 macOS Catalina 最新官方正式版下载 / Mac 10.15 操作系统 dmg 镜像\nmacOS Mojave 正式版操作系统下载 - 苹果最新 Mac 系统升级程序 dmg 镜像\nmacOS High Sierra 正式版下载 - 苹果最新 Mac 系统升级程序官方原版镜像\n\n异次元正版数字商城  |  异次元首页  |  微信公众号  |  iPcFun  |  关注微博  |  软件精选",
          "link": "https://www.iplaysoft.com/macos-monterey.html",
          "publishedOn": "2021-07-01T10:52:06.000Z",
          "wordCount": 825,
          "title": "苹果 macOS Monterey 最新官方公测版下载 - Mac 12.0 操作系统 dmg 镜像"
        },
        {
          "id": "https://www.iplaysoft.com/?p=3143",
          "author": "X-Force",
          "description": "在之前的发布会上，苹果正式公布了最新的 iOS 15、iPadOS 以及 macOS Monterey 三大新版操作系统，继 Windows 11 后，苹果终于也推出「公测版固件下载」让我们换换口味了。\n据网友反馈 iOS 15、iPadOS 公测版的完成度较高，感兴趣的用户都可以升级尝鲜了！iOS 15 支持主流的 iPhone / iPad 机型，提供了很多新功能特性，如实时识别照片文字、鼠标键盘“跨设备”通用操控、SharePlay 与朋友一起看剧听歌、专注模式等；加上之前的 AirPods 虚拟环绕声、Apple Pencil 手写文字识别等黑科技，十分值得你提前升级感受……\n「 前往查看原文.... 」\n异次元还有这些值得一看：\n\n苹果最新 iOS 14.5 正式版 / iPadOS 固件 IPSW 全套官方下载地址 (升级 iPhone iPad 系统)\n首款 iOS 虚拟机 UTM - 免越狱在 iPhone iPad 上安装 Windows / Linux / 安卓系统\niOS 11 正式版有什么新功能？全部新功能特性评测+体验视频\n苹果 iOS 9.3.3 完美一键越狱 - 盘古越狱工具软件下载+图文教程 (iPhone/iPad)\n\n异次元正版数字商城  |  异次元首页  |  微信公众号  |  iPcFun  |  关注微博  |  软件精选",
          "link": "https://www.iplaysoft.com/ios-beta.html",
          "publishedOn": "2021-07-01T09:20:13.000Z",
          "wordCount": 921,
          "title": "苹果 iOS 15 / iPadOS 最新官方公测版固件 IPSW 下载升级降级与恢复教程"
        },
        {
          "id": "https://www.iplaysoft.com/?p=5501",
          "author": "X-Force",
          "description": "曾几何时，为了提升一点 APP 的启动速度，很多人还是愿意花费高价去购买性能强劲的手机的。而现在倒好，就算你花再多钱买贵手机，不等个 3、5 秒的开屏广告也别想用 APP 了。\n这让我们每天使用手机，都不可避免地被这些粗制滥造的广告重复地恶心无数次。这些开屏广告不仅拖慢 APP 的启动速度、浪费流量和电量，一不小心点错可能还会自动下载或者唤起其他 APP，非常让人反感。其实，我们可以借助「轻启动」来自动跳过这些恶心的启动广告……\n「 前往查看原文.... 」\n异次元还有这些值得一看：\n\n黑域 - 可能是最好的安卓省电防卡顿工具！不用Root禁止APP后台唤醒自启动\n冰箱 Ice Box - 手机省电利器！防止 Android 应用后台偷跑流量/耗电/卡顿的工具\n手机照片泄露被偷拍你还傻傻不知道？用这款良心的隐私风险自测 APP 试试吧\n边缘任务 - 让你的安卓手机拥有超方便的全面屏手势操作 (无需 root 权限)\n\n异次元正版数字商城  |  异次元首页  |  微信公众号  |  iPcFun  |  关注微博  |  软件精选",
          "link": "https://www.iplaysoft.com/qing-qi-dong.html",
          "publishedOn": "2021-06-29T18:18:36.000Z",
          "wordCount": 540,
          "title": "轻启动 (免费/完整版) - 自动点击跳过 APP 开屏广告 / 免等待倒计时加速启动安卓应用"
        },
        {
          "id": "https://www.iplaysoft.com/?post_type=xpost&p=5183",
          "author": "X-Force",
          "description": "国内云计算厂商，平时一般很少有给力活动，每到 618 大促期间，不仅 京东、淘宝、爱奇艺、腾讯视频、哔哩哔哩、PD16 以及等一众软件特价优惠陆续出现之外，像 腾讯云、阿里云、Vultr 等服务器的打折力度都会相当的疯狂！遇到神价好价的机会非常多。\n\n而这次「腾讯云的  618 年中大促」力度媲美双 …… \n「 前往查看原文.... 」\n\n异次元正版数字商城  |  异次元首页  |  微信公众号  |  iPcFun  |  关注微博  |  软件精选",
          "link": "https://www.iplaysoft.com/p/qcloud-sale",
          "publishedOn": "2021-06-27T16:40:38.000Z",
          "wordCount": 455,
          "title": "腾讯云 618 “秒杀良心价” 活动袭来 - 便宜购买国内服务器"
        },
        {
          "id": "https://www.iplaysoft.com/?post_type=xpost&p=5505",
          "author": "X-Force",
          "description": "最近微软正式发布了最新的 Windows 11 操作系统，全新的 UI 界面、支持运行 Android 应用等特性还是很吸引人的，目前镜像也已可下载了，不少人都跃跃欲试。\n\n访问：微软中国官网\n但是 Win11 对电脑的硬件配置还是有点要求的，并不是每台电脑都能顺利安装。相比以往死板的配置要求列表，微软官方这次…… \n「 前往查看原文.... 」\n\n异次元正版数字商城  |  异次元首页  |  微信公众号  |  iPcFun  |  关注微博  |  软件精选",
          "link": "https://www.iplaysoft.com/p/pc-health-check",
          "publishedOn": "2021-06-27T04:17:30.000Z",
          "wordCount": 502,
          "title": "测试电脑能否安装运行 Win11 - 微软免费硬件检查测试工具"
        },
        {
          "id": "https://www.iplaysoft.com/?post_type=news&p=5454",
          "author": "X-Force",
          "description": "由于之前挖矿盛行导致了除显卡 以及 硬盘 的价格都全面疯涨！国内外的电商硬盘价格基本上都无法按正常价格购买，对于急需硬盘的朋友真的非常懊恼。而这次，亚马逊海外购终于出现了回落，这对大伙来说绝对是一波“及时雨”啊。\n\n如果你有购买硬盘存储设备的需求，无论是用于电脑、NAS 或备份…… \n「 前往查看原文.... 」\n\n异次元正版数字商城  |  异次元首页  |  微信公众号  |  iPcFun  |  关注微博  |  软件精选",
          "link": "https://www.iplaysoft.com/news/5454",
          "publishedOn": "2021-06-22T06:05:17.000Z",
          "wordCount": 483,
          "title": "矿难已至？！硬盘终于跌了！10TB 1297 元，刚需速抢……"
        },
        {
          "id": "https://www.iplaysoft.com/?p=5371",
          "author": "X-Force",
          "description": "在如今的短视频时代，很多人都想要快速地制作大量视频。但一般制作一个视频还得要花上不少时间的，而借助 AI 人工智能则可以帮你简化制作过程，大幅提高视频产出效率。\n「万彩微影」正是一款通过 AI 智能全自动生成短视频的软件合集！它包括图文动画视频制作工具、抖音手绘视频制作工具、文字视频制作工具。方便你快速生成多种原创短视频，让你轻松上传到各大视频平台来快速传播，增加粉丝、赚取佣金、或者更快更好地卖货……\n「 前往查看原文.... 」\n异次元还有这些值得一看：\n\n万彩字影大师限免 - 自媒体抖音文字动画视频制作软件 (免费领取特别版激活码)\n快速好用的制作动画视频软件 - 万彩动画大师 (限时送激活注册码)\n万彩动画大师正版激活码 - 小白都能上手！简单快速的短视频动画制作软件\nFocusky 动画演示大师 - 制作炫酷动画 PPT 的软件 (限时送特别版激活码)\n\n异次元正版数字商城  |  异次元首页  |  微信公众号  |  iPcFun  |  关注微博  |  软件精选",
          "link": "https://www.iplaysoft.com/wan-cai-wei-ying.html",
          "publishedOn": "2021-06-21T17:19:46.000Z",
          "wordCount": 481,
          "title": "AI 智能自动生成短视频的软件 - 万彩微影送特别版会员 (图文转视频/影视剪辑/手绘)"
        },
        {
          "id": "https://www.iplaysoft.com/?post_type=xpost&p=5500",
          "author": "X-Force",
          "description": "在刚刚结束的 618 大促期间，腾讯云、阿里云服务器，爱奇艺+京东PLUS、腾讯视频、哔哩哔哩会员，以及 Parallels Desktop 虚拟机、Eagle、IDM 等软件都出现了超值好价。而今天我们发现「亚马逊海外购」居然开始“错峰发力”了！！\n\n亚马逊将于 6 月 20~23 日开启「亚马逊 Prime 会员日」，带来了相当多价格劲…… \n「 前往查看原文.... 」\n\n异次元正版数字商城  |  异次元首页  |  微信公众号  |  iPcFun  |  关注微博  |  软件精选",
          "link": "https://www.iplaysoft.com/p/amazon-prime-day",
          "publishedOn": "2021-06-21T12:51:45.000Z",
          "wordCount": 973,
          "title": "群晖 NAS / 三星 980 固态史低 - 亚马逊大量「历史低价」清单释出"
        },
        {
          "id": "https://www.iplaysoft.com/?p=5499",
          "author": "X-Force",
          "description": "我们知道苹果在发布新的 Mac / iOS 系统时都会包含一些全新的内置壁纸，异次元都会提供它们全套新壁纸打包下载。比如 iOS15 + macOS Monterey 壁纸、iOS14 + Big Sur 壁纸等。\n其实微软也不例外！在最新推出的 Windows 11 操作系统里，视觉上最大的变化就是它内置了一套全新的 Win11 默认桌面壁纸，包含了深色和浅色主题的高清版本，风格简约好看，上机效果相当不错！如果你暂未打算安装新系统体验，那么提前下载 Win11 自带壁纸来感受一下吧……\n「 前往查看原文.... 」\n异次元还有这些值得一看：\n\n全套苹果 iOS 15 内置壁纸 / macOS Monterey 超高清 6K 默认桌面壁纸打包下载\n微软 Win10 预览版全新 “隐藏” 壁纸 + Build 开发者大会主题壁纸全套打包下载\n苹果 iOS 14.2 新增耳目一新的壁纸！全新风格 iPhone 12 桌面内置壁纸全套下载\n全套苹果 iOS 14 内置壁纸 / macOS Big Sur 超高清 6K 默认桌面壁纸打包下载\n\n异次元正版数字商城  |  异次元首页  |  微信公众号  |  iPcFun  |  关注微博  |  软件精选",
          "link": "https://www.iplaysoft.com/windows11-wallpapers.html",
          "publishedOn": "2021-06-21T06:19:47.000Z",
          "wordCount": 504,
          "title": "微软 Windows 11 全套内置自带壁纸打包下载 - Win11 官方默认原生 4K 高清壁纸图片"
        },
        {
          "id": "https://www.iplaysoft.com/?post_type=news&p=4313",
          "author": "X-Force",
          "description": "如果你经常会在京东商城买东西，一定知道京东 Plus 会员的各种好处！比如每月免邮运费券、全品类优惠券、Plus 特价商品、专享活动价、免费上门退换货等等特权。\n\n但原本京东正式 PLUS 会员的定价是 299 元/年，正价购买还是比较贵的。而这次爱奇艺京东联名会员搞促销，现在限时 5折以 278 元买爱奇…… \n「 前往查看原文.... 」\n\n异次元正版数字商城  |  异次元首页  |  微信公众号  |  iPcFun  |  关注微博  |  软件精选",
          "link": "https://www.iplaysoft.com/news/4313",
          "publishedOn": "2021-06-20T13:05:32.000Z",
          "wordCount": null,
          "title": "限时 5 折！爱奇艺 (电视端) VIP 年卡 + 京东 Plus 会员 = 278 元"
        },
        {
          "id": "https://www.iplaysoft.com/parallels.html",
          "author": "X-Force",
          "description": "Parallels Desktop 被称为 macOS 上最强大的虚拟机软件。可以在 Mac 下同时模拟运行 Win、Linux、Android 等多种操作系统及软件而不必重启电脑，并能在不同系统间随意切换。\n最新版的 Parallels Desktop 16 (PD16) 完美支持最新的 macOS Big Sur 并对 Windows 10 特别优化！可不重启直接在 Mac 系统上运行 Win10 UWP 通用应用、运行游戏、使用 Windows 版软件如 Office 办公软件、IE 浏览器、VisualStudio、AutoCAD 等。新版 PD16 支持 DirectX 11，大幅提升了启动速度以及 3D 游戏图形性能！！绝对是 Mac 用户必备神器……\n「 前往查看原文.... 」\n异次元还有这些值得一看：\n\nVMWare Fusion Pro 12 / Player 官方免费版 - 苹果 macOS 虚拟机软件 (Big Sur/Win10)\nVMware Workstation Pro 16 中文虚拟机软件专业版 - 支持最新 Win10/游戏3D加速\nPortable VirtualBox - 免费绿色版虚拟机软件 / 制作免安装的便携U盘系统\nVMWare Player 16 中文版 - 官方免费版虚拟机软件 (支持3D游戏与Win10系统)\n\n异次元正版数字商城  |  异次元首页  |  微信公众号  |  iPcFun  |  关注微博  |  软件精选",
          "link": "https://www.iplaysoft.com/parallels-desktop.html",
          "publishedOn": "2021-06-19T18:01:40.000Z",
          "wordCount": 1586,
          "title": "Parallels Desktop 16.5 最新版下载 - Mac 系统最强虚拟机 (支持M1/Win10/macOS Big Sur)"
        },
        {
          "id": "https://www.iplaysoft.com/?p=4858",
          "author": "X-Force",
          "description": "《Overcooked! 2》被译为「胡闹厨房 2」或「煮糊了」，单从这游戏名字来看，似乎并不那么吸引人。但实际上，它真的是一个非常非常有趣的游戏！强烈建议情侣、基友们一起玩玩！\n胡闹厨房又称为“分手厨房”，是一款超欢乐的多人合作模拟厨房游戏，你将和朋友们分工合作一起从切菜、煮菜到上菜的过程，由于时间紧迫、各种搞怪突发事件加上玩家们手残操作，整个过程会非常欢乐搞笑，如果没有合理分工和默契配合，你们将面临手忙脚乱和残酷的撕逼……\n「 前往查看原文.... 」\n异次元还有这些值得一看：\n\n模拟人生 4 中文版 - 经典 PC 游戏大作！在虚拟世界体验别样人生\n地平线：零之曙光完整版 (中文) - 索尼良心！居然免费送这么厉害的科幻动作游戏\n低价买正版游戏 Steam 激活码方法 - Humble Bundle Choice 月度游戏优惠包\nCEMU - 电脑上流畅玩任天堂 Wii U 游戏模拟器 (塞尔达传说荒野之息 / 马里奥等)\n\n异次元正版数字商城  |  异次元首页  |  微信公众号  |  iPcFun  |  关注微博  |  软件精选",
          "link": "https://www.iplaysoft.com/overcooked.html",
          "publishedOn": "2021-06-19T06:01:18.000Z",
          "wordCount": null,
          "title": "胡闹厨房 2 (分手厨房 / 煮糊了) - 超欢乐搞笑的本地合作游戏！享受友尽撕逼的快乐"
        },
        {
          "id": "https://www.iplaysoft.com/?p=5292",
          "author": "X-Force",
          "description": "「百度网盘限速」一直是大家日常上网和办公都绕不开的话题，毕竟像 115 网盘、城通网盘以及迅雷云盘等都没对它的市场份额构成什么实质的威胁，不过现在它的大敌终于来了。\n阿里巴巴近日推出了「阿里云盘」网盘产品以及 APP 应用，并正式开始了公测！依靠于阿里云服务器的技术、带宽、基础设施以及背后的财力，阿里云盘官方甚至承诺了上传下载均“永不限速”，可以预见它将拥有与百度网盘直面竞争的能力……\n「 前往查看原文.... 」\n异次元还有这些值得一看：\n\n微力同步 - 跨平台文件同步软件 Resilio Sync 替代品 (电脑/手机/NAS)\nNextcloud - 搭建个人专属或团队共享的私有云同步网盘 (开源免费跨平台)\n百度网盘官方最新“免费不限速”方法！免破解无需会员下载提速/客户端加速设置\n迅雷云盘 - 免费支持 BT 磁力离线下载+在线视频播放 / 可替代 115 百度网盘？\n\n异次元正版数字商城  |  异次元首页  |  微信公众号  |  iPcFun  |  关注微博  |  软件精选",
          "link": "https://www.iplaysoft.com/aliyundrive.html",
          "publishedOn": "2021-06-18T16:19:33.000Z",
          "wordCount": 845,
          "title": "阿里云盘客户端下载 - 号称永不限速！福利码兑换可增加免费空间 (替代百度网盘)"
        },
        {
          "id": "https://www.iplaysoft.com/?post_type=xpost&p=5479",
          "author": "X-Force",
          "description": "每年年中最大的促销活动「6·18 大促」差不多又要到来了。从六月开始，包括京东、天猫、亚马逊、苏宁、网易考拉海淘等电商就会开始陆续地开启一波又一波优惠攻势了。\n\n红包领取入口：\n一：领取京东 618 红包\n二：天猫 618 活动会场\n\n618 「正版软件」优惠汇总收集\n最后一波：爱奇艺 + 京东 Plus 会员…… \n「 前往查看原文.... 」\n\n异次元正版数字商城  |  异次元首页  |  微信公众号  |  iPcFun  |  关注微博  |  软件精选",
          "link": "https://www.iplaysoft.com/p/618",
          "publishedOn": "2021-06-16T16:55:02.000Z",
          "wordCount": null,
          "title": "618 值得买的好价汇总！会员/软件/优惠整理收集贴"
        }
      ]
    },
    {
      "title": "大眼仔旭",
      "feedUrl": "http://www.dayanzai.me/feed",
      "siteUrl": "http://www.dayanzai.me",
      "articles": [
        {
          "id": "http://www.dayanzai.me/?p=53154",
          "author": "大眼仔~旭",
          "description": "大眼仔旭（www.dayanzai.me）给大家推荐分享正版 Wise Care 365 PRO。Wise C […]",
          "link": "http://www.dayanzai.me/wise-care-365.html",
          "publishedOn": "2021-07-14T02:41:44.000Z",
          "wordCount": 559,
          "title": "官方正版赠品 Wise Care 365 PRO 中文版免费领取"
        },
        {
          "id": "http://www.dayanzai.me/?p=31988",
          "author": "大眼仔~旭",
          "description": "推荐语：“刘遄老师的新书《Linux就该这么学》双十一当天预售出版上市，必读的Linux系统和红帽认证自学书籍 […]",
          "link": "http://www.dayanzai.me/linux-book.html",
          "publishedOn": "2021-07-13T18:28:33.000Z",
          "wordCount": 495,
          "title": "《Linux就该这么学》— 非常适合linux技术学习的入门好书"
        },
        {
          "id": "http://www.dayanzai.me/?p=40528",
          "author": "大眼仔~旭",
          "description": "正版特价！仅需 348 元！洗白白这次错过下次就不知道什么时间了！数量和时间都有限！现在绝大部分网友应该使用的 […]",
          "link": "http://www.dayanzai.me/windows-10-buy.html",
          "publishedOn": "2021-07-13T17:20:37.000Z",
          "wordCount": 699,
          "title": "微软官方特价！Windows 10 Pro 专业版 仅需 348 元！绑定数字权利、支持迁移授权！"
        },
        {
          "id": "http://www.dayanzai.me/?p=36715",
          "author": "大眼仔~旭",
          "description": "由本站和APSGO软购商城推荐的官方正版特价！终身版！Office 家庭和学生版 2016/2019 正版办公 […]",
          "link": "http://www.dayanzai.me/office-buy.html",
          "publishedOn": "2021-07-13T16:58:44.000Z",
          "wordCount": 649,
          "title": "官方正版 Office 2016/2019 家庭和学生版，底价限量促销！仅 98 元！终身使用！"
        },
        {
          "id": "http://www.dayanzai.me/?p=47188",
          "author": "大眼仔~旭",
          "description": "“站在风口，猪都会飞”。这是如今层出不穷创业公司梦寐以求的，而经历疫情洗礼之后的风口，远程办公毫无疑问算是一类 […]",
          "link": "http://www.dayanzai.me/sunloginclient.html",
          "publishedOn": "2021-07-13T16:53:56.000Z",
          "wordCount": 579,
          "title": "送会员兑换码 – 简单好用的远控神器，国产向日葵轻松开启远程办公！"
        },
        {
          "id": "http://www.dayanzai.me/?p=39529",
          "author": "大眼仔~旭",
          "description": "微软开源免费代码编辑器 Visual Studio Code 中文版由大眼仔旭（www.dayanzai.me […]",
          "link": "http://www.dayanzai.me/visual-studio-code.html",
          "publishedOn": "2021-07-13T16:39:26.000Z",
          "wordCount": 602,
          "title": "微软开源免费代码编辑器 Visual Studio Code 1.58.1 + x64 中文多语免费版"
        },
        {
          "id": "http://www.dayanzai.me/?p=4645",
          "author": "大眼仔~旭",
          "description": "Win10 任务栏搜索增强工具  EverythingToolbar 中文版由大眼仔旭（www.dayanza […]",
          "link": "http://www.dayanzai.me/everythingtoolbar.html",
          "publishedOn": "2021-07-13T16:29:39.000Z",
          "wordCount": 719,
          "title": "Windows 10 增强搜索工具栏 EverythingToolbar 0.7.1 中文免费版"
        },
        {
          "id": "http://www.dayanzai.me/?p=2062",
          "author": "大眼仔~旭",
          "description": "EmEditor 中文版 今天小编（www.dayanzai.me）大眼仔旭给大家介绍一款简单好用的文本编辑器 […]",
          "link": "http://www.dayanzai.me/emeditor-pro.html",
          "publishedOn": "2021-07-13T16:16:58.000Z",
          "wordCount": 695,
          "title": "优秀代码编辑器 EmEditor Professional 20.9.0 + x64 中文免费版"
        },
        {
          "id": "http://www.dayanzai.me/?p=8637",
          "author": "大眼仔~旭",
          "description": "水狐浏览器 Waterfox 中文版由大眼仔旭（www.dayanzai.me）发布。Waterfox 中文版 […]",
          "link": "http://www.dayanzai.me/waterfox.html",
          "publishedOn": "2021-07-13T16:13:52.000Z",
          "wordCount": 606,
          "title": "水狐浏览器 Waterfox G3.2.3.1/2021.07 Classic x64 中文免费版"
        },
        {
          "id": "http://www.dayanzai.me/?p=5639",
          "author": "大眼仔~旭",
          "description": "SD Maid Pro 中文版 Android SD 卡管理工具由大眼仔旭（www.dayanzai.me）发 […]",
          "link": "http://www.dayanzai.me/sd-maid-pro.html",
          "publishedOn": "2021-07-12T16:45:08.000Z",
          "wordCount": 542,
          "title": "Android SD 卡管理工具 SD Maid 5.1.5 中文多语免费版"
        }
      ]
    },
    {
      "title": "精品绿色便携软件",
      "feedUrl": "http://www.portablesoft.org/feed/",
      "siteUrl": "https://www.portablesoft.org",
      "articles": []
    },
    {
      "title": "The Portable Freeware Collection",
      "feedUrl": "http://feeds.feedburner.com/pfc",
      "siteUrl": "https://www.portablefreeware.com/",
      "articles": [
        {
          "id": "1388+1626270747",
          "author": null,
          "description": "",
          "link": "https://www.portablefreeware.com/?id=1388&ts=1626270747",
          "publishedOn": "2021-07-14T13:52:27.000Z",
          "wordCount": 1091,
          "title": "[UPDATE] SIV v5.59"
        },
        {
          "id": "2956+1626267336",
          "author": null,
          "description": "",
          "link": "https://www.portablefreeware.com/?id=2956&ts=1626267336",
          "publishedOn": "2021-07-14T12:55:36.000Z",
          "wordCount": 530,
          "title": "[UPDATE] Beeftext v9.1"
        },
        {
          "id": "2286+1626267285",
          "author": null,
          "description": "",
          "link": "https://www.portablefreeware.com/?id=2286&ts=1626267285",
          "publishedOn": "2021-07-14T12:54:45.000Z",
          "wordCount": 555,
          "title": "[UPDATE] QuickTextPaste v7.41"
        },
        {
          "id": "132+1626240043",
          "author": null,
          "description": "",
          "link": "https://www.portablefreeware.com/?id=132&ts=1626240043",
          "publishedOn": "2021-07-14T05:20:43.000Z",
          "wordCount": 5293,
          "title": "[UPDATE] Mozilla Firefox, Portable Edition v90.0"
        },
        {
          "id": "2832+1626204728",
          "author": null,
          "description": "",
          "link": "https://www.portablefreeware.com/?id=2832&ts=1626204728",
          "publishedOn": "2021-07-13T19:32:08.000Z",
          "wordCount": 1028,
          "title": "[UPDATE] PDF-XChange Editor v9.1.355.0"
        },
        {
          "id": "1345+1626174934",
          "author": null,
          "description": "",
          "link": "https://www.portablefreeware.com/?id=1345&ts=1626174934",
          "publishedOn": "2021-07-13T11:15:34.000Z",
          "wordCount": 2419,
          "title": "[UPDATE] Pidgin Portable v2.14.6"
        },
        {
          "id": "2753+1626174878",
          "author": null,
          "description": "",
          "link": "https://www.portablefreeware.com/?id=2753&ts=1626174878",
          "publishedOn": "2021-07-13T11:14:38.000Z",
          "wordCount": 545,
          "title": "[UPDATE] WifiHistoryView v1.60"
        },
        {
          "id": "1750+1626174746",
          "author": null,
          "description": "",
          "link": "https://www.portablefreeware.com/?id=1750&ts=1626174746",
          "publishedOn": "2021-07-13T11:12:26.000Z",
          "wordCount": 447,
          "title": "[UPDATE] NK2Edit v3.42"
        },
        {
          "id": "2155+1626091774",
          "author": null,
          "description": "",
          "link": "https://www.portablefreeware.com/?id=2155&ts=1626091774",
          "publishedOn": "2021-07-12T12:09:34.000Z",
          "wordCount": 615,
          "title": "[UPDATE] NetworkTrafficView v2.41"
        },
        {
          "id": "2633+1626091730",
          "author": null,
          "description": "",
          "link": "https://www.portablefreeware.com/?id=2633&ts=1626091730",
          "publishedOn": "2021-07-12T12:08:50.000Z",
          "wordCount": 1242,
          "title": "[UPDATE] Slimjet v31.0.0"
        },
        {
          "id": "2417+1626091660",
          "author": null,
          "description": "",
          "link": "https://www.portablefreeware.com/?id=2417&ts=1626091660",
          "publishedOn": "2021-07-12T12:07:40.000Z",
          "wordCount": 626,
          "title": "[UPDATE] Database .NET v32.8"
        },
        {
          "id": "2560+1626091619",
          "author": null,
          "description": "",
          "link": "https://www.portablefreeware.com/?id=2560&ts=1626091619",
          "publishedOn": "2021-07-12T12:06:59.000Z",
          "wordCount": 488,
          "title": "[UPDATE] FBCacheView v1.21"
        },
        {
          "id": "2521+1626019382",
          "author": null,
          "description": "",
          "link": "https://www.portablefreeware.com/?id=2521&ts=1626019382",
          "publishedOn": "2021-07-11T16:03:02.000Z",
          "wordCount": 700,
          "title": "[UPDATE] Info-Base v11.2"
        },
        {
          "id": "816+1626007984",
          "author": null,
          "description": "",
          "link": "https://www.portablefreeware.com/?id=816&ts=1626007984",
          "publishedOn": "2021-07-11T12:53:04.000Z",
          "wordCount": 1486,
          "title": "[UPDATE] ToDoList v8.0.23"
        },
        {
          "id": "2392+1625999269",
          "author": null,
          "description": "",
          "link": "https://www.portablefreeware.com/?id=2392&ts=1625999269",
          "publishedOn": "2021-07-11T10:27:49.000Z",
          "wordCount": 734,
          "title": "[UPDATE] Tor Browser v10.5"
        },
        {
          "id": "1535+1625999134",
          "author": null,
          "description": "",
          "link": "https://www.portablefreeware.com/?id=1535&ts=1625999134",
          "publishedOn": "2021-07-11T10:25:34.000Z",
          "wordCount": 1513,
          "title": "[UPDATE] HashMyFiles v2.41"
        },
        {
          "id": "1443+1625999095",
          "author": null,
          "description": "",
          "link": "https://www.portablefreeware.com/?id=1443&ts=1625999095",
          "publishedOn": "2021-07-11T10:24:55.000Z",
          "wordCount": 3885,
          "title": "[UPDATE] XMedia Recode v3.5.3.9"
        },
        {
          "id": "9+1625940636",
          "author": null,
          "description": "",
          "link": "https://www.portablefreeware.com/?id=9&ts=1625940636",
          "publishedOn": "2021-07-10T18:10:36.000Z",
          "wordCount": 1577,
          "title": "[UPDATE] FileZilla v3.55.0"
        },
        {
          "id": "1431+1625924593",
          "author": null,
          "description": "",
          "link": "https://www.portablefreeware.com/?id=1431&ts=1625924593",
          "publishedOn": "2021-07-10T13:43:13.000Z",
          "wordCount": 5016,
          "title": "[UPDATE] Q-Dir v9.77"
        },
        {
          "id": "2119+1625857555",
          "author": null,
          "description": "",
          "link": "https://www.portablefreeware.com/?id=2119&ts=1625857555",
          "publishedOn": "2021-07-09T19:05:55.000Z",
          "wordCount": 1340,
          "title": "[UPDATE] calibre v5.23"
        },
        {
          "id": "1692+1625842731",
          "author": null,
          "description": "",
          "link": "https://www.portablefreeware.com/?id=1692&ts=1625842731",
          "publishedOn": "2021-07-09T14:58:51.000Z",
          "wordCount": 1201,
          "title": "[UPDATE] DesktopOK v9.11"
        },
        {
          "id": "2350+1625756696",
          "author": null,
          "description": "",
          "link": "https://www.portablefreeware.com/?id=2350&ts=1625756696",
          "publishedOn": "2021-07-08T15:04:56.000Z",
          "wordCount": 680,
          "title": "[UPDATE] PrivaZer v4.0.27"
        },
        {
          "id": "2208+1625682091",
          "author": null,
          "description": "",
          "link": "https://www.portablefreeware.com/?id=2208&ts=1625682091",
          "publishedOn": "2021-07-07T18:21:31.000Z",
          "wordCount": 1481,
          "title": "[UPDATE] PhraseExpress v15.0.90"
        },
        {
          "id": "2890+1625658087",
          "author": null,
          "description": "",
          "link": "https://www.portablefreeware.com/?id=2890&ts=1625658087",
          "publishedOn": "2021-07-07T11:41:27.000Z",
          "wordCount": 951,
          "title": "[UPDATE] CudaText v1.137.2"
        },
        {
          "id": "2895+1625658018",
          "author": null,
          "description": "",
          "link": "https://www.portablefreeware.com/?id=2895&ts=1625658018",
          "publishedOn": "2021-07-07T11:40:18.000Z",
          "wordCount": 658,
          "title": "[UPDATE] ScreenToGif v2.32.1"
        },
        {
          "id": "2543+1625657892",
          "author": null,
          "description": "",
          "link": "https://www.portablefreeware.com/?id=2543&ts=1625657892",
          "publishedOn": "2021-07-07T11:38:12.000Z",
          "wordCount": 668,
          "title": "[UPDATE] Extra Keys v2.2.4"
        },
        {
          "id": "2089+1625657734",
          "author": null,
          "description": "",
          "link": "https://www.portablefreeware.com/?id=2089&ts=1625657734",
          "publishedOn": "2021-07-07T11:35:34.000Z",
          "wordCount": 1080,
          "title": "[UPDATE] SeaMonkey, Portable Edition v2.53.8"
        },
        {
          "id": "1193+1625614446",
          "author": null,
          "description": "",
          "link": "https://www.portablefreeware.com/?id=1193&ts=1625614446",
          "publishedOn": "2021-07-06T23:34:06.000Z",
          "wordCount": 2653,
          "title": "[UPDATE] SumatraPDF v3.3"
        },
        {
          "id": "2080+1625595653",
          "author": null,
          "description": "",
          "link": "https://www.portablefreeware.com/?id=2080&ts=1625595653",
          "publishedOn": "2021-07-06T18:20:53.000Z",
          "wordCount": 889,
          "title": "[UPDATE] XnConvert v1.92.0"
        },
        {
          "id": "1715+1625575492",
          "author": null,
          "description": "",
          "link": "https://www.portablefreeware.com/?id=1715&ts=1625575492",
          "publishedOn": "2021-07-06T12:44:52.000Z",
          "wordCount": 769,
          "title": "[UPDATE] HWiNFO v7.06"
        },
        {
          "id": "777+1625575470",
          "author": null,
          "description": "",
          "link": "https://www.portablefreeware.com/?id=777&ts=1625575470",
          "publishedOn": "2021-07-06T12:44:30.000Z",
          "wordCount": 699,
          "title": "[UPDATE] Mail PassView v1.92"
        },
        {
          "id": "1791+1625575299",
          "author": null,
          "description": "",
          "link": "https://www.portablefreeware.com/?id=1791&ts=1625575299",
          "publishedOn": "2021-07-06T12:41:39.000Z",
          "wordCount": 605,
          "title": "[UPDATE] AllDup v4.4.56"
        },
        {
          "id": "3053+1625575219",
          "author": null,
          "description": "",
          "link": "https://www.portablefreeware.com/?id=3053&ts=1625575219",
          "publishedOn": "2021-07-06T12:40:19.000Z",
          "wordCount": 444,
          "title": "[UPDATE] Homedale v1.97"
        },
        {
          "id": "2733+1625461517",
          "author": null,
          "description": "",
          "link": "https://www.portablefreeware.com/?id=2733&ts=1625461517",
          "publishedOn": "2021-07-05T05:05:17.000Z",
          "wordCount": 830,
          "title": "[UPDATE] Xlideit Image Viewer v1.0.210214"
        },
        {
          "id": "2186+1625461300",
          "author": null,
          "description": "",
          "link": "https://www.portablefreeware.com/?id=2186&ts=1625461300",
          "publishedOn": "2021-07-05T05:01:40.000Z",
          "wordCount": 592,
          "title": "[UPDATE] SavageEd2 v0.6.03"
        },
        {
          "id": "539+1625423647",
          "author": null,
          "description": "",
          "link": "https://www.portablefreeware.com/?id=539&ts=1625423647",
          "publishedOn": "2021-07-04T18:34:07.000Z",
          "wordCount": 5847,
          "title": "[UPDATE] Notepad++ v8.1.1"
        },
        {
          "id": "2781+1625406625",
          "author": null,
          "description": "",
          "link": "https://www.portablefreeware.com/?id=2781&ts=1625406625",
          "publishedOn": "2021-07-04T13:50:25.000Z",
          "wordCount": 821,
          "title": "[UPDATE] Tablacus Explorer v21.7.4"
        },
        {
          "id": "2757+1625399516",
          "author": null,
          "description": "",
          "link": "https://www.portablefreeware.com/?id=2757&ts=1625399516",
          "publishedOn": "2021-07-04T11:51:56.000Z",
          "wordCount": 428,
          "title": "[UPDATE] Detect It Easy v3.02"
        },
        {
          "id": "644+1625375659",
          "author": null,
          "description": "",
          "link": "https://www.portablefreeware.com/?id=644&ts=1625375659",
          "publishedOn": "2021-07-04T05:14:19.000Z",
          "wordCount": 1108,
          "title": "[UPDATE] GIMP Portable v2.10.24-3"
        },
        {
          "id": "2304+1625372263",
          "author": null,
          "description": "",
          "link": "https://www.portablefreeware.com/?id=2304&ts=1625372263",
          "publishedOn": "2021-07-04T04:17:43.000Z",
          "wordCount": 673,
          "title": "[UPDATE] Multi Commander v11.2"
        },
        {
          "id": "2156+1625364518",
          "author": null,
          "description": "",
          "link": "https://www.portablefreeware.com/?id=2156&ts=1625364518",
          "publishedOn": "2021-07-04T02:08:38.000Z",
          "wordCount": 706,
          "title": "[UPDATE] CSVFileView v2.53"
        },
        {
          "id": "1441+1625335458",
          "author": null,
          "description": "",
          "link": "https://www.portablefreeware.com/?id=1441&ts=1625335458",
          "publishedOn": "2021-07-03T18:04:18.000Z",
          "wordCount": 1011,
          "title": "[UPDATE] CrystalDiskInfo v8.12.3"
        },
        {
          "id": "2892+1625285721",
          "author": null,
          "description": "",
          "link": "https://www.portablefreeware.com/?id=2892&ts=1625285721",
          "publishedOn": "2021-07-03T04:15:21.000Z",
          "wordCount": 510,
          "title": "[UPDATE] StorURL v3.0.34.1"
        },
        {
          "id": "36+1625227264",
          "author": null,
          "description": "",
          "link": "https://www.portablefreeware.com/?id=36&ts=1625227264",
          "publishedOn": "2021-07-02T12:01:04.000Z",
          "wordCount": 1155,
          "title": "[UPDATE] TreeSize Free v4.5"
        },
        {
          "id": "2816+1625222725",
          "author": null,
          "description": "",
          "link": "https://www.portablefreeware.com/?id=2816&ts=1625222725",
          "publishedOn": "2021-07-02T10:45:25.000Z",
          "wordCount": 541,
          "title": "[UPDATE] QOwnNotes v21.7.2"
        },
        {
          "id": "2406+1625222622",
          "author": null,
          "description": "",
          "link": "https://www.portablefreeware.com/?id=2406&ts=1625222622",
          "publishedOn": "2021-07-02T10:43:42.000Z",
          "wordCount": 1716,
          "title": "[UPDATE] qBittorrent v4.3.6"
        },
        {
          "id": "2301+1625222429",
          "author": null,
          "description": "",
          "link": "https://www.portablefreeware.com/?id=2301&ts=1625222429",
          "publishedOn": "2021-07-02T10:40:29.000Z",
          "wordCount": 497,
          "title": "[UPDATE] OutlookAddressBookView v2.32"
        },
        {
          "id": "214+1625079966",
          "author": null,
          "description": "",
          "link": "https://www.portablefreeware.com/?id=214&ts=1625079966",
          "publishedOn": "2021-06-30T19:06:06.000Z",
          "wordCount": 914,
          "title": "[UPDATE] WinSCP v5.19.1"
        },
        {
          "id": "2402+1625051060",
          "author": null,
          "description": "",
          "link": "https://www.portablefreeware.com/?id=2402&ts=1625051060",
          "publishedOn": "2021-06-30T11:04:20.000Z",
          "wordCount": 467,
          "title": "[UPDATE] Run-Command v4.99"
        },
        {
          "id": "2734+1625051004",
          "author": null,
          "description": "",
          "link": "https://www.portablefreeware.com/?id=2734&ts=1625051004",
          "publishedOn": "2021-06-30T11:03:24.000Z",
          "wordCount": 446,
          "title": "[UPDATE] AdvancedRun v1.24"
        },
        {
          "id": "1738+1625050914",
          "author": null,
          "description": "",
          "link": "https://www.portablefreeware.com/?id=1738&ts=1625050914",
          "publishedOn": "2021-06-30T11:01:54.000Z",
          "wordCount": 890,
          "title": "[UPDATE] Don't Sleep v8.44"
        },
        {
          "id": "1421+1625050785",
          "author": null,
          "description": "",
          "link": "https://www.portablefreeware.com/?id=1421&ts=1625050785",
          "publishedOn": "2021-06-30T10:59:45.000Z",
          "wordCount": 587,
          "title": "[UPDATE] GnuCash Portable v4.6"
        },
        {
          "id": "3038+1625050705",
          "author": null,
          "description": "",
          "link": "https://www.portablefreeware.com/?id=3038&ts=1625050705",
          "publishedOn": "2021-06-30T10:58:25.000Z",
          "wordCount": 432,
          "title": "[UPDATE] ConEmu v21.06.27"
        },
        {
          "id": "98+1624963529",
          "author": null,
          "description": "",
          "link": "https://www.portablefreeware.com/?id=98&ts=1624963529",
          "publishedOn": "2021-06-29T10:45:29.000Z",
          "wordCount": 2807,
          "title": "[UPDATE] EssentialPIM Free v9.9.6"
        },
        {
          "id": "2835+1624912219",
          "author": null,
          "description": "",
          "link": "https://www.portablefreeware.com/?id=2835&ts=1624912219",
          "publishedOn": "2021-06-28T20:30:19.000Z",
          "wordCount": 555,
          "title": "[UPDATE] DxWnd v2.05.72"
        },
        {
          "id": "3050+1624889883",
          "author": null,
          "description": "",
          "link": "https://www.portablefreeware.com/?id=3050&ts=1624889883",
          "publishedOn": "2021-06-28T14:18:03.000Z",
          "wordCount": 406,
          "title": "[NEW] SUMo Portable V5.12.16"
        },
        {
          "id": "570+1624852468",
          "author": null,
          "description": "",
          "link": "https://www.portablefreeware.com/?id=570&ts=1624852468",
          "publishedOn": "2021-06-28T03:54:28.000Z",
          "wordCount": 2854,
          "title": "[UPDATE] fre:ac v1.1.5"
        },
        {
          "id": "1950+1624796132",
          "author": null,
          "description": "",
          "link": "https://www.portablefreeware.com/?id=1950&ts=1624796132",
          "publishedOn": "2021-06-27T12:15:32.000Z",
          "wordCount": 2863,
          "title": "[UPDATE] pestudio standard v9.13"
        },
        {
          "id": "2859+1624795899",
          "author": null,
          "description": "",
          "link": "https://www.portablefreeware.com/?id=2859&ts=1624795899",
          "publishedOn": "2021-06-27T12:11:39.000Z",
          "wordCount": 482,
          "title": "[UPDATE] Kid3 v3.8.7"
        },
        {
          "id": "1004+1624795771",
          "author": null,
          "description": "",
          "link": "https://www.portablefreeware.com/?id=1004&ts=1624795771",
          "publishedOn": "2021-06-27T12:09:31.000Z",
          "wordCount": 1559,
          "title": "[UPDATE] USBDeview v3.02"
        },
        {
          "id": "2571+1624785104",
          "author": null,
          "description": "",
          "link": "https://www.portablefreeware.com/?id=2571&ts=1624785104",
          "publishedOn": "2021-06-27T09:11:44.000Z",
          "wordCount": 1497,
          "title": "[UPDATE] Tixati v2.84"
        },
        {
          "id": "1691+1624714924",
          "author": null,
          "description": "",
          "link": "https://www.portablefreeware.com/?id=1691&ts=1624714924",
          "publishedOn": "2021-06-26T13:42:04.000Z",
          "wordCount": 971,
          "title": "[UPDATE] Blank And Secure v6.44"
        },
        {
          "id": "1409+1624679325",
          "author": null,
          "description": "",
          "link": "https://www.portablefreeware.com/?id=1409&ts=1624679325",
          "publishedOn": "2021-06-26T03:48:45.000Z",
          "wordCount": 901,
          "title": "[UPDATE] SideSlide v4.93"
        },
        {
          "id": "2502+1624622031",
          "author": null,
          "description": "",
          "link": "https://www.portablefreeware.com/?id=2502&ts=1624622031",
          "publishedOn": "2021-06-25T11:53:51.000Z",
          "wordCount": 481,
          "title": "[UPDATE] WinLogOnView v1.40"
        },
        {
          "id": "2377+1624621959",
          "author": null,
          "description": "",
          "link": "https://www.portablefreeware.com/?id=2377&ts=1624621959",
          "publishedOn": "2021-06-25T11:52:39.000Z",
          "wordCount": 3054,
          "title": "[UPDATE] FileOptimizer v15.00"
        },
        {
          "id": "2239+1624621797",
          "author": null,
          "description": "",
          "link": "https://www.portablefreeware.com/?id=2239&ts=1624621797",
          "publishedOn": "2021-06-25T11:49:57.000Z",
          "wordCount": 549,
          "title": "[UPDATE] MeinPlatz v7.01"
        },
        {
          "id": "2033+1624545290",
          "author": null,
          "description": "",
          "link": "https://www.portablefreeware.com/?id=2033&ts=1624545290",
          "publishedOn": "2021-06-24T14:34:50.000Z",
          "wordCount": 526,
          "title": "[UPDATE] muCommander v0.9.7"
        },
        {
          "id": "90+1624545096",
          "author": null,
          "description": "",
          "link": "https://www.portablefreeware.com/?id=90&ts=1624545096",
          "publishedOn": "2021-06-24T14:31:36.000Z",
          "wordCount": 1918,
          "title": "[UPDATE] 1by1 v1.99"
        },
        {
          "id": "1959+1624530344",
          "author": null,
          "description": "",
          "link": "https://www.portablefreeware.com/?id=1959&ts=1624530344",
          "publishedOn": "2021-06-24T10:25:44.000Z",
          "wordCount": 595,
          "title": "[UPDATE] Lightscreen v2.5"
        },
        {
          "id": "1960+1624529278",
          "author": null,
          "description": "",
          "link": "https://www.portablefreeware.com/?id=1960&ts=1624529278",
          "publishedOn": "2021-06-24T10:07:58.000Z",
          "wordCount": 618,
          "title": "[UPDATE] ColorConsole v5.85"
        },
        {
          "id": "1408+1624529166",
          "author": null,
          "description": "",
          "link": "https://www.portablefreeware.com/?id=1408&ts=1624529166",
          "publishedOn": "2021-06-24T10:06:06.000Z",
          "wordCount": 629,
          "title": "[UPDATE] VideoCacheView v3.07"
        },
        {
          "id": "1552+1624529099",
          "author": null,
          "description": "",
          "link": "https://www.portablefreeware.com/?id=1552&ts=1624529099",
          "publishedOn": "2021-06-24T10:04:59.000Z",
          "wordCount": 517,
          "title": "[UPDATE] DevManView v1.75"
        },
        {
          "id": "2758+1624387809",
          "author": null,
          "description": "",
          "link": "https://www.portablefreeware.com/?id=2758&ts=1624387809",
          "publishedOn": "2021-06-22T18:50:09.000Z",
          "wordCount": 473,
          "title": "[UPDATE] EMDB v4.08"
        },
        {
          "id": "1033+1624384503",
          "author": null,
          "description": "",
          "link": "https://www.portablefreeware.com/?id=1033&ts=1624384503",
          "publishedOn": "2021-06-22T17:55:03.000Z",
          "wordCount": 1105,
          "title": "[UPDATE] Process Monitor v3.83"
        },
        {
          "id": "2360+1624270245",
          "author": null,
          "description": "",
          "link": "https://www.portablefreeware.com/?id=2360&ts=1624270245",
          "publishedOn": "2021-06-21T10:10:45.000Z",
          "wordCount": 1437,
          "title": "[UPDATE] WizTree v4.01"
        },
        {
          "id": "2973+1624243254",
          "author": null,
          "description": "",
          "link": "https://www.portablefreeware.com/?id=2973&ts=1624243254",
          "publishedOn": "2021-06-21T02:40:54.000Z",
          "wordCount": 482,
          "title": "[UPDATE] SmartSystemMenu v2.6.1"
        },
        {
          "id": "599+1624130627",
          "author": null,
          "description": "",
          "link": "https://www.portablefreeware.com/?id=599&ts=1624130627",
          "publishedOn": "2021-06-19T19:23:47.000Z",
          "wordCount": 3997,
          "title": "[UPDATE] VLC v3.0.16"
        },
        {
          "id": "2055+1624101342",
          "author": null,
          "description": "",
          "link": "https://www.portablefreeware.com/?id=2055&ts=1624101342",
          "publishedOn": "2021-06-19T11:15:42.000Z",
          "wordCount": 5225,
          "title": "[UPDATE] LibreOffice Portable v7.1.4"
        },
        {
          "id": "2494+1624101288",
          "author": null,
          "description": "",
          "link": "https://www.portablefreeware.com/?id=2494&ts=1624101288",
          "publishedOn": "2021-06-19T11:14:48.000Z",
          "wordCount": 533,
          "title": "[UPDATE] TurnedOnTimesView v1.45"
        },
        {
          "id": "2960+1624101217",
          "author": null,
          "description": "",
          "link": "https://www.portablefreeware.com/?id=2960&ts=1624101217",
          "publishedOn": "2021-06-19T11:13:37.000Z",
          "wordCount": 454,
          "title": "[UPDATE] EmEditor Free v20.9"
        },
        {
          "id": "2298+1624101048",
          "author": null,
          "description": "",
          "link": "https://www.portablefreeware.com/?id=2298&ts=1624101048",
          "publishedOn": "2021-06-19T11:10:48.000Z",
          "wordCount": 593,
          "title": "[UPDATE] Windows File Analyzer v2.9.0"
        },
        {
          "id": "2604+1624040148",
          "author": null,
          "description": "",
          "link": "https://www.portablefreeware.com/?id=2604&ts=1624040148",
          "publishedOn": "2021-06-18T18:15:48.000Z",
          "wordCount": 472,
          "title": "[UPDATE] Magnifixer v10.2"
        },
        {
          "id": "1698+1624039844",
          "author": null,
          "description": "",
          "link": "https://www.portablefreeware.com/?id=1698&ts=1624039844",
          "publishedOn": "2021-06-18T18:10:44.000Z",
          "wordCount": 895,
          "title": "[UPDATE] OneLoupe v5.01"
        },
        {
          "id": "2677+1624021380",
          "author": null,
          "description": "",
          "link": "https://www.portablefreeware.com/?id=2677&ts=1624021380",
          "publishedOn": "2021-06-18T13:03:00.000Z",
          "wordCount": 590,
          "title": "[UPDATE] Strong Passwords Need Entropy v18.0"
        },
        {
          "id": "1989+1624021133",
          "author": null,
          "description": "",
          "link": "https://www.portablefreeware.com/?id=1989&ts=1624021133",
          "publishedOn": "2021-06-18T12:58:53.000Z",
          "wordCount": 755,
          "title": "[UPDATE] Virtual Volumes View Portable v1.4"
        },
        {
          "id": "2810+1624021039",
          "author": null,
          "description": "",
          "link": "https://www.portablefreeware.com/?id=2810&ts=1624021039",
          "publishedOn": "2021-06-18T12:57:19.000Z",
          "wordCount": 444,
          "title": "[UPDATE] EventLogChannelsView v1.35"
        },
        {
          "id": "2811+1623873084",
          "author": null,
          "description": "",
          "link": "https://www.portablefreeware.com/?id=2811&ts=1623873084",
          "publishedOn": "2021-06-16T19:51:24.000Z",
          "wordCount": 441,
          "title": "[UPDATE] FullEventLogView v1.62"
        },
        {
          "id": "1952+1623846914",
          "author": null,
          "description": "",
          "link": "https://www.portablefreeware.com/?id=1952&ts=1623846914",
          "publishedOn": "2021-06-16T12:35:14.000Z",
          "wordCount": 1367,
          "title": "[UPDATE] MobaXterm Home Edition v21.2"
        },
        {
          "id": "3052+1623762071",
          "author": null,
          "description": "",
          "link": "https://www.portablefreeware.com/?id=3052&ts=1623762071",
          "publishedOn": "2021-06-15T13:01:11.000Z",
          "wordCount": 413,
          "title": "[UPDATE] O&O ShutUp10 V1.8 Build 1422"
        }
      ]
    },
    {
      "title": "QiuQuan's Blog",
      "feedUrl": "http://www.qiuquan.cc/feed",
      "siteUrl": "http://www.qiuquan.cc",
      "articles": [
        {
          "id": "http://w.qiuquan.cc/?p=178",
          "author": "qiuquan",
          "description": "驱动人生是一款免费的驱动管理软件，实现智能检测硬件并自动查找安装驱动，为用户提供最新驱动更新，本机驱动备份、还原和卸载等功能。软件界面清晰，操作简单，设置人性化等优点，大大方便广大机友管理自己的电脑的驱动程序。",
          "link": "http://www.qiuquan.cc/inside/drivethelife.html",
          "publishedOn": "2021-07-14T01:40:46.000Z",
          "wordCount": 349,
          "title": "驱动人生 7.2.4.16 +  8.3.39.160 去广告版（破解VIP极速下载权限）（安装版 + 单文件版）"
        },
        {
          "id": "http://w.qiuquan.cc/?p=325",
          "author": "qiuquan",
          "description": "Enigma Virtual Box 虚拟文件打包系统（Windows 环境）可以将您的程序和配套文件打包成一个可执行文件，而没有任何效率的损失，配套文件也不会被释放至硬盘。本项功能有独立的免费应用程序，同时支持 X86 和 X64 二进制文件。",
          "link": "http://www.qiuquan.cc/setup/enigma-virtual-box.html",
          "publishedOn": "2021-07-14T01:14:35.000Z",
          "wordCount": 198,
          "title": "虚拟化单文件打包工具——Enigma Virtual Box 9.70 汉化单文件版 By：th_sjy"
        },
        {
          "id": "http://w.qiuquan.cc/?p=188",
          "author": "qiuquan",
          "description": "腾讯视频播放器是腾讯视频旗下的客户端产品，是一款支持丰富内容的在线点播及电视台直播的软件。它采用了先进的P2P流媒体播放技术，可以确保在大量用户同时观看节目的情况下，节目依然流畅清晰；同时具有很强的防火墙穿透能力，为用户在任何网络环境下收看流畅的视频节目提供了有力保障。",
          "link": "http://www.qiuquan.cc/inside/qqlive.html",
          "publishedOn": "2021-07-14T01:05:12.000Z",
          "wordCount": 580,
          "title": "腾讯视频 11.25.3008 去广告精简版"
        },
        {
          "id": "http://w.qiuquan.cc/?p=340",
          "author": "qiuquan",
          "description": "Adobe Flash Player浏览器专用的flash播放器插件,可以播放Adobe Flash制作的flash文件,运行时，它可以跨浏览器和操作系统、原汁原味地呈现具有表现力的应用程序、内容和视频，功能强大，兼容性高。",
          "link": "http://www.qiuquan.cc/media/flash.html",
          "publishedOn": "2021-07-13T06:40:42.000Z",
          "wordCount": 232,
          "title": "Adobe Flash Player 32.0.0.465 国际版（和谐地区限制版） + 34.0.0.175 国内特供版（去除广告&支持 Win7/10 IE）（ActiveX + NPAPI + PPAPI）"
        },
        {
          "id": "http://w.qiuquan.cc/?p=141",
          "author": "qiuquan",
          "description": "Allavsoft 视频下载器 是一个流行的快速在线视频下载和转换器，以帮助用户快速下载和转换在线电影，让其能在PC、便携式设备，、手机、MP4播放器、电视上更轻松地播放。 强大的视频下载工具可以保存高清，HQ和3D电影在线视频，然后转换为MP4，AVI，WMV，MOV，MKV，FLV，MPG，VOB等，以在各种各样的数码设备播放，包括ipad mini， iPad，iPod，iPhone，谷歌Nexus，Microsoft Surface，Kindle Fire，黑莓，苹果电视，Zune，PSP，PS3，掌上电脑，创意Zen，Xbox，Archos等。",
          "link": "http://www.qiuquan.cc/convert/allavsoft.html",
          "publishedOn": "2021-07-13T01:35:33.000Z",
          "wordCount": 190,
          "title": "视频下载转换利器——Allavsoft Video Downloader Converter 3.23.7.7852 注册版"
        },
        {
          "id": "http://w.qiuquan.cc/?p=101",
          "author": "qiuquan",
          "description": "PotPlayer 是 KMPlayer 的原制作者姜龙喜先生（韩国）进入 Daum 公司后的新一代作品。PotPlayer 的优势在于强大的内置解码器；而 KMPlayer 的优势在于强大的定制能力和个性化功能。PotPlayer 使用 VC++ 编写， KMPlayer 为 Delphi 编写。",
          "link": "http://www.qiuquan.cc/media/potplayer.html",
          "publishedOn": "2021-07-13T01:35:25.000Z",
          "wordCount": 766,
          "title": "Daum PotPlayer 1.7.21482 正式版 + 1.7.21512 测试版｜美化版｜安装版 (去TV列表&禁止强制升级)"
        },
        {
          "id": "http://w.qiuquan.cc/?p=205",
          "author": "qiuquan",
          "description": "AshampooWinOptimizer是一款性能强劲、功能全面的Windows系统优化清理工具。AshampooWinOptimizer具有调整和优化系统性能、驱动器清理、Dll文件清理、注册表清理、上网纪录清理、弹出窗口过滤、网络加速、启动加速、磁盘碎片整理、启动项目管理、进程监控、安全删除重要文件、检查并还原已被删除的文件、文件的加密和解密、系统图标和桌面设置、显示测试比较系统性能、文件的分割和合并、备份和恢复等众多功能，还具备一键优化的快捷功能；而且官方完美的提供了中文支持，界面甚是清爽怡人。",
          "link": "http://www.qiuquan.cc/systemtool/ashampoo-winoptimizer.html",
          "publishedOn": "2021-07-13T00:50:48.000Z",
          "wordCount": 296,
          "title": "专业系统优化工具——Ashampoo WinOptimizer 17.00.32 + 18.00.18 + 19.00.13 破解版"
        },
        {
          "id": "http://w.qiuquan.cc/?p=115",
          "author": "qiuquan",
          "description": "360浏览器是互联网上好用和安全的新一代浏览器，和360安全卫士、360杀毒等软件等产品一同成为360安全中心的系列产品。木马已经取代病毒成为当前互联网上最大的威胁，90%的木马用挂马网站通过普通浏览器入侵，每天有200万用户访问挂马网站中毒。",
          "link": "http://www.qiuquan.cc/browser/360se.html",
          "publishedOn": "2021-07-12T09:10:50.000Z",
          "wordCount": 918,
          "title": "360安全浏览器 13.1.1456.0 正式版 v2 + 13.1.3052.0 测试版｜去广告优化版（预置Flash插件为 34.0.0.164 国内特供和谐版）"
        },
        {
          "id": "http://w.qiuquan.cc/?p=301",
          "author": "qiuquan",
          "description": "阿里旺旺专为淘宝会员量身定做的个人交易沟通软件，方便买家和卖家在交易过程实时进行沟通。可以进行文字聊天、语音聊天、视频聊天、文件传输、发送离线文件等。",
          "link": "http://www.qiuquan.cc/chat/aliim.html",
          "publishedOn": "2021-07-12T08:25:13.000Z",
          "wordCount": 253,
          "title": "阿里旺旺2021（9.12.12C）去广告精简版"
        },
        {
          "id": "http://w.qiuquan.cc/?p=265",
          "author": "qiuquan",
          "description": "360软件管家，为用户打造了一站式下载安装软件的平台。软件宝库收录的每款软件都经过人工安装验证，通过卡巴、NOD32、360杀毒等国内外知名杀软的联合查杀，确保无毒、无木马，用户尽可放心下载。360软件管家升级能第一时间提醒用户下载升级软件新版本，大大节省寻找和下载软件新版本的时间。",
          "link": "http://www.qiuquan.cc/systemtool/360softmgr.html",
          "publishedOn": "2021-07-12T06:35:47.000Z",
          "wordCount": 392,
          "title": "360软件管家 7.5.0.1750 独立版安装版（支持组件下载）"
        }
      ]
    }
  ],
  "cliVersion": "1.11.0"
}